[{"reg":"84","libelle":"Auvergne-Rhône-Alpes","values":{"nb-utilisateurs-pass-culture":{"value":167552,"value_date":"2022-12-31"}},"nb-utilisateurs-pass-culture":[{"date":"2021-04-30","value":113723},{"date":"2022-03-31","value":108553},{"date":"2022-04-30","value":113722},{"date":"2022-05-31","value":120000},{"date":"2022-06-30","value":126209},{"date":"2022-07-31","value":131812},{"date":"2022-08-31","value":138959},{"date":"2022-09-30","value":146972},{"date":"2022-10-31","value":146961},{"date":"2022-11-30","value":160553},{"date":"2022-12-31","value":167552}],"targets":{"nb-utilisateurs-pass-culture":{"target":182811,"target_date":"2022-12-31"}}},{"reg":"32","libelle":"Hauts-de-France","values":{"nb-utilisateurs-pass-culture":{"value":148682,"value_date":"2022-12-31"}},"nb-utilisateurs-pass-culture":[{"date":"2021-04-30","value":102501},{"date":"2022-03-31","value":97867},{"date":"2022-04-30","value":102500},{"date":"2022-05-31","value":108043},{"date":"2022-06-30","value":113189},{"date":"2022-07-31","value":118340},{"date":"2022-08-31","value":124445},{"date":"2022-09-30","value":130784},{"date":"2022-10-31","value":130778},{"date":"2022-11-30","value":142741},{"date":"2022-12-31","value":148682}],"targets":{"nb-utilisateurs-pass-culture":{"target":148568,"target_date":"2022-12-31"}}},{"reg":"93","libelle":"Provence-Alpes-Côte d'Azur","values":{"nb-utilisateurs-pass-culture":{"value":103148,"value_date":"2022-12-31"}},"nb-utilisateurs-pass-culture":[{"date":"2022-03-31","value":67520},{"date":"2022-04-30","value":70602},{"date":"2022-05-31","value":74528},{"date":"2022-06-30","value":78238},{"date":"2022-07-31","value":81617},{"date":"2022-08-31","value":85792},{"date":"2022-09-30","value":90408},{"date":"2022-10-31","value":90398},{"date":"2022-11-30","value":98912},{"date":"2022-12-31","value":103148}],"targets":{"nb-utilisateurs-pass-culture":{"target":109608,"target_date":"2022-12-31"}}},{"reg":"44","libelle":"Grand Est","values":{"nb-utilisateurs-pass-culture":{"value":127587,"value_date":"2022-12-31"}},"nb-utilisateurs-pass-culture":[{"date":"2021-04-30","value":91454},{"date":"2022-03-31","value":87796},{"date":"2022-04-30","value":91453},{"date":"2022-05-31","value":95942},{"date":"2022-06-30","value":99956},{"date":"2022-07-31","value":103934},{"date":"2022-08-31","value":108776},{"date":"2022-09-30","value":113971},{"date":"2022-10-31","value":113965},{"date":"2022-11-30","value":123224},{"date":"2022-12-31","value":127587}],"targets":{"nb-utilisateurs-pass-culture":{"target":125311,"target_date":"2022-12-31"}}},{"reg":"76","libelle":"Occitanie","values":{"nb-utilisateurs-pass-culture":{"value":135750,"value_date":"2022-12-31"}},"nb-utilisateurs-pass-culture":[{"date":"2021-04-30","value":95876},{"date":"2022-03-31","value":91894},{"date":"2022-04-30","value":95874},{"date":"2022-05-31","value":100477},{"date":"2022-06-30","value":104815},{"date":"2022-07-31","value":109003},{"date":"2022-08-31","value":114484},{"date":"2022-09-30","value":120275},{"date":"2022-10-31","value":120268},{"date":"2022-11-30","value":130431},{"date":"2022-12-31","value":135750}],"targets":{"nb-utilisateurs-pass-culture":{"target":133466,"target_date":"2022-12-31"}}},{"reg":"28","libelle":"Normandie","values":{"nb-utilisateurs-pass-culture":{"value":69428,"value_date":"2022-12-31"}},"nb-utilisateurs-pass-culture":[{"date":"2021-04-30","value":47371},{"date":"2022-03-31","value":45220},{"date":"2022-04-30","value":47370},{"date":"2022-05-31","value":50147},{"date":"2022-06-30","value":52540},{"date":"2022-07-31","value":54962},{"date":"2022-08-31","value":57949},{"date":"2022-09-30","value":60907},{"date":"2022-10-31","value":60902},{"date":"2022-11-30","value":66498},{"date":"2022-12-31","value":69428}],"targets":{"nb-utilisateurs-pass-culture":{"target":77094,"target_date":"2022-12-31"}}},{"reg":"75","libelle":"Nouvelle-Aquitaine","values":{"nb-utilisateurs-pass-culture":{"value":124190,"value_date":"2022-12-31"}},"nb-utilisateurs-pass-culture":[{"date":"2021-04-30","value":83844},{"date":"2022-03-31","value":79890},{"date":"2022-04-30","value":83843},{"date":"2022-05-31","value":88696},{"date":"2022-06-30","value":93254},{"date":"2022-07-31","value":97504},{"date":"2022-08-31","value":102832},{"date":"2022-09-30","value":108407},{"date":"2022-10-31","value":108396},{"date":"2022-11-30","value":118652},{"date":"2022-12-31","value":124190}],"targets":{"nb-utilisateurs-pass-culture":{"target":131340,"target_date":"2022-12-31"}}},{"reg":"24","libelle":"Centre-Val de Loire","values":{"nb-utilisateurs-pass-culture":{"value":54847,"value_date":"2022-12-31"}},"nb-utilisateurs-pass-culture":[{"date":"2021-04-30","value":37445},{"date":"2022-04-30","value":37444},{"date":"2022-05-31","value":39642},{"date":"2022-06-30","value":41615},{"date":"2022-07-31","value":43613},{"date":"2022-08-31","value":45958},{"date":"2022-09-30","value":48267},{"date":"2022-10-31","value":48262},{"date":"2022-11-30","value":52548},{"date":"2022-12-31","value":54847}],"targets":{"nb-utilisateurs-pass-culture":{"target":55291,"target_date":"2022-12-31"}}},{"reg":"27","libelle":"Bourgogne-Franche-Comté","values":{"nb-utilisateurs-pass-culture":{"value":65566,"value_date":"2022-12-31"}},"nb-utilisateurs-pass-culture":[{"date":"2021-04-30","value":47201},{"date":"2022-03-31","value":45275},{"date":"2022-04-30","value":47201},{"date":"2022-05-31","value":49408},{"date":"2022-06-30","value":51550},{"date":"2022-07-31","value":53630},{"date":"2022-08-31","value":56140},{"date":"2022-09-30","value":58624},{"date":"2022-10-31","value":58616},{"date":"2022-11-30","value":63187},{"date":"2022-12-31","value":65566}],"targets":{"nb-utilisateurs-pass-culture":{"target":62023,"target_date":"2022-12-31"}}},{"reg":"53","libelle":"Bretagne","values":{"nb-utilisateurs-pass-culture":{"value":130260,"value_date":"2022-12-31"}},"nb-utilisateurs-pass-culture":[{"date":"2021-04-30","value":103878},{"date":"2022-03-31","value":101131},{"date":"2022-04-30","value":103877},{"date":"2022-05-31","value":107128},{"date":"2022-06-30","value":110256},{"date":"2022-07-31","value":113085},{"date":"2022-08-31","value":116711},{"date":"2022-09-30","value":120157},{"date":"2022-10-31","value":120143},{"date":"2022-11-30","value":126398},{"date":"2022-12-31","value":130260}],"targets":{"nb-utilisateurs-pass-culture":{"target":76565,"target_date":"2022-12-31"}}},{"reg":"94","libelle":"Corse","values":{"nb-utilisateurs-pass-culture":{"value":2772,"value_date":"2022-12-31"}},"nb-utilisateurs-pass-culture":[{"date":"2021-04-30","value":1896},{"date":"2021-05-31","value":716},{"date":"2021-06-30","value":983},{"date":"2021-07-31","value":1088},{"date":"2021-08-31","value":1163},{"date":"2021-09-30","value":1218},{"date":"2021-10-31","value":1269},{"date":"2021-11-30","value":1324},{"date":"2022-03-31","value":1803},{"date":"2022-04-30","value":1896},{"date":"2022-05-31","value":1982},{"date":"2022-06-30","value":2078},{"date":"2022-07-31","value":2169},{"date":"2022-08-31","value":2280},{"date":"2022-09-30","value":2416},{"date":"2022-10-31","value":2415},{"date":"2022-11-30","value":2633},{"date":"2022-12-31","value":2772}],"targets":{"nb-utilisateurs-pass-culture":{"target":5991,"target_date":"2022-12-31"}}},{"reg":"52","libelle":"Pays de la Loire","values":{"nb-utilisateurs-pass-culture":{"value":85319,"value_date":"2022-12-31"}},"nb-utilisateurs-pass-culture":[{"date":"2021-04-30","value":56752},{"date":"2022-03-31","value":54170},{"date":"2022-04-30","value":56752},{"date":"2022-05-31","value":60190},{"date":"2022-06-30","value":63231},{"date":"2022-07-31","value":66233},{"date":"2022-08-31","value":70112},{"date":"2022-09-30","value":74200},{"date":"2022-10-31","value":74190},{"date":"2022-11-30","value":81472},{"date":"2022-12-31","value":85319}],"targets":{"nb-utilisateurs-pass-culture":{"target":87781,"target_date":"2022-12-31"}}},{"reg":"11","libelle":"Île-de-France","values":{"nb-utilisateurs-pass-culture":{"value":328395,"value_date":"2022-12-31"}},"nb-utilisateurs-pass-culture":[{"date":"2021-04-30","value":233149},{"date":"2022-03-31","value":224236},{"date":"2022-04-30","value":233149},{"date":"2022-05-31","value":244522},{"date":"2022-06-30","value":255373},{"date":"2022-07-31","value":265600},{"date":"2022-08-31","value":277655},{"date":"2022-09-30","value":290897},{"date":"2022-10-31","value":290875},{"date":"2022-11-30","value":316194},{"date":"2022-12-31","value":328395}],"targets":{"nb-utilisateurs-pass-culture":{"target":280188,"target_date":"2022-12-31"}}},{"reg":"01","libelle":"Guadeloupe","values":{"nb-utilisateurs-pass-culture":{"value":6761,"value_date":"2022-12-31"}},"nb-utilisateurs-pass-culture":[{"date":"2021-04-30","value":3586},{"date":"2022-03-31","value":3271},{"date":"2022-04-30","value":3586},{"date":"2022-05-31","value":4006},{"date":"2022-06-30","value":4409},{"date":"2022-07-31","value":5026},{"date":"2022-08-31","value":5269},{"date":"2022-09-30","value":5464},{"date":"2022-10-31","value":5464},{"date":"2022-11-30","value":6343},{"date":"2022-12-31","value":6761}],"targets":{"nb-utilisateurs-pass-culture":{"target":9898,"target_date":"2022-12-31"}}},{"reg":"02","libelle":"Martinique","values":{"nb-utilisateurs-pass-culture":{"value":5756,"value_date":"2022-12-31"}},"nb-utilisateurs-pass-culture":[{"date":"2021-04-30","value":3214},{"date":"2022-03-31","value":2610},{"date":"2022-04-30","value":3214},{"date":"2022-05-31","value":3579},{"date":"2022-06-30","value":3922},{"date":"2022-07-31","value":4317},{"date":"2022-08-31","value":4658},{"date":"2022-09-30","value":4887},{"date":"2022-10-31","value":4887},{"date":"2022-11-30","value":5482},{"date":"2022-12-31","value":5756}],"targets":{"nb-utilisateurs-pass-culture":{"target":8882,"target_date":"2022-12-31"}}},{"reg":"03","libelle":"Guyane","values":{"nb-utilisateurs-pass-culture":{"value":3588,"value_date":"2022-12-31"}},"nb-utilisateurs-pass-culture":[{"date":"2021-04-30","value":2443},{"date":"2022-03-31","value":2274},{"date":"2022-04-30","value":2443},{"date":"2022-05-31","value":2604},{"date":"2022-06-30","value":2782},{"date":"2022-07-31","value":2938},{"date":"2022-08-31","value":3066},{"date":"2022-09-30","value":3172},{"date":"2022-10-31","value":3172},{"date":"2022-11-30","value":3465},{"date":"2022-12-31","value":3588}],"targets":{"nb-utilisateurs-pass-culture":{"target":8952,"target_date":"2022-12-31"}}},{"reg":"04","libelle":"La Réunion","values":{"nb-utilisateurs-pass-culture":{"value":18445,"value_date":"2022-12-31"}},"nb-utilisateurs-pass-culture":[{"date":"2021-04-30","value":11895},{"date":"2022-03-31","value":11167},{"date":"2022-04-30","value":11895},{"date":"2022-05-31","value":12842},{"date":"2022-06-30","value":13687},{"date":"2022-07-31","value":14546},{"date":"2022-08-31","value":15465},{"date":"2022-09-30","value":16229},{"date":"2022-10-31","value":16227},{"date":"2022-11-30","value":17746},{"date":"2022-12-31","value":18445}],"targets":{"nb-utilisateurs-pass-culture":{"target":24238,"target_date":"2022-12-31"}}},{"reg":"06","libelle":"Mayotte","values":{"nb-utilisateurs-pass-culture":{"value":668,"value_date":"2022-12-31"}},"nb-utilisateurs-pass-culture":[{"date":"2021-04-30","value":383},{"date":"2022-03-31","value":334},{"date":"2022-04-30","value":383},{"date":"2022-05-31","value":437},{"date":"2022-06-30","value":476},{"date":"2022-07-31","value":518},{"date":"2022-08-31","value":562},{"date":"2022-09-30","value":600},{"date":"2022-10-31","value":600},{"date":"2022-11-30","value":648},{"date":"2022-12-31","value":668}],"targets":{"nb-utilisateurs-pass-culture":{"target":9437,"target_date":"2022-12-31"}}}]
