[{"dep":"01","libelle":"Ain","values":{"nb-attestations-savoir-rouler-velo":{"value":352,"value_date":"2021-09-30"},"nb-cycle-aisance-aquatique":{"value":214,"value_date":"2020-12-31"}},"nb-attestations-savoir-rouler-velo":[{"date":"2017-12-31","value":0},{"date":"2018-12-31","value":0},{"date":"2019-03-31","value":0},{"date":"2019-04-30","value":0},{"date":"2020-11-30","value":0},{"date":"2020-12-31","value":20},{"date":"2021-01-31","value":20},{"date":"2021-02-28","value":20},{"date":"2021-03-31","value":29},{"date":"2021-06-30","value":323},{"date":"2021-09-30","value":352}],"nb-cycle-aisance-aquatique":[{"date":"2020-12-31","value":214}],"targets":{"nb-cycle-aisance-aquatique":{"target":941,"target_date":"2022-12-31"},"nb-attestations-savoir-rouler-velo":{"target":2098,"target_date":"2022-12-31"}}},{"dep":"02","libelle":"Aisne","values":{"nb-attestations-savoir-rouler-velo":{"value":1283,"value_date":"2021-09-30"},"nb-cycle-aisance-aquatique":{"value":0,"value_date":"2020-12-31"}},"nb-attestations-savoir-rouler-velo":[{"date":"2017-12-31","value":0},{"date":"2018-12-31","value":0},{"date":"2019-03-31","value":0},{"date":"2019-04-30","value":0},{"date":"2020-11-30","value":134},{"date":"2020-12-31","value":134},{"date":"2021-01-31","value":134},{"date":"2021-02-28","value":134},{"date":"2021-03-31","value":163},{"date":"2021-06-30","value":1105},{"date":"2021-09-30","value":1283}],"nb-cycle-aisance-aquatique":[{"date":"2020-12-31","value":0}],"targets":{"nb-cycle-aisance-aquatique":{"target":722,"target_date":"2022-12-31"},"nb-attestations-savoir-rouler-velo":{"target":1618,"target_date":"2022-12-31"}}},{"dep":"03","libelle":"Allier","values":{"nb-attestations-savoir-rouler-velo":{"value":1437,"value_date":"2021-09-30"},"nb-cycle-aisance-aquatique":{"value":42,"value_date":"2020-12-31"}},"nb-attestations-savoir-rouler-velo":[{"date":"2017-12-31","value":0},{"date":"2018-12-31","value":0},{"date":"2019-03-31","value":0},{"date":"2019-04-30","value":0},{"date":"2020-11-30","value":0},{"date":"2020-12-31","value":0},{"date":"2021-01-31","value":0},{"date":"2021-02-28","value":0},{"date":"2021-03-31","value":38},{"date":"2021-06-30","value":890},{"date":"2021-09-30","value":1437}],"nb-cycle-aisance-aquatique":[{"date":"2020-12-31","value":42}],"targets":{"nb-cycle-aisance-aquatique":{"target":371,"target_date":"2022-12-31"},"nb-attestations-savoir-rouler-velo":{"target":820,"target_date":"2022-12-31"}}},{"dep":"04","libelle":"Alpes-de-Haute-Provence","values":{"nb-attestations-savoir-rouler-velo":{"value":36,"value_date":"2021-09-30"},"nb-cycle-aisance-aquatique":{"value":0,"value_date":"2020-12-31"}},"nb-attestations-savoir-rouler-velo":[{"date":"2017-12-31","value":0},{"date":"2018-12-31","value":0},{"date":"2019-03-31","value":0},{"date":"2019-04-30","value":0},{"date":"2020-11-30","value":21},{"date":"2020-12-31","value":21},{"date":"2021-01-31","value":21},{"date":"2021-02-28","value":21},{"date":"2021-03-31","value":22},{"date":"2021-06-30","value":36},{"date":"2021-09-30","value":36}],"nb-cycle-aisance-aquatique":[{"date":"2020-12-31","value":0}],"targets":{"nb-cycle-aisance-aquatique":{"target":189,"target_date":"2022-12-31"},"nb-attestations-savoir-rouler-velo":{"target":436,"target_date":"2022-12-31"}}},{"dep":"05","libelle":"Hautes-Alpes","values":{"nb-attestations-savoir-rouler-velo":{"value":388,"value_date":"2021-09-30"},"nb-cycle-aisance-aquatique":{"value":0,"value_date":"2020-12-31"}},"nb-attestations-savoir-rouler-velo":[{"date":"2017-12-31","value":0},{"date":"2018-12-31","value":0},{"date":"2019-03-31","value":0},{"date":"2019-04-30","value":0},{"date":"2020-11-30","value":41},{"date":"2020-12-31","value":41},{"date":"2021-01-31","value":41},{"date":"2021-02-28","value":41},{"date":"2021-03-31","value":46},{"date":"2021-06-30","value":344},{"date":"2021-09-30","value":388}],"nb-cycle-aisance-aquatique":[{"date":"2020-12-31","value":0}],"targets":{"nb-cycle-aisance-aquatique":{"target":163,"target_date":"2022-12-31"},"nb-attestations-savoir-rouler-velo":{"target":373,"target_date":"2022-12-31"}}},{"dep":"06","libelle":"Alpes-Maritimes","values":{"nb-attestations-savoir-rouler-velo":{"value":497,"value_date":"2021-09-30"},"nb-cycle-aisance-aquatique":{"value":98,"value_date":"2020-12-31"}},"nb-attestations-savoir-rouler-velo":[{"date":"2017-12-31","value":0},{"date":"2018-12-31","value":0},{"date":"2019-03-31","value":0},{"date":"2019-04-30","value":0},{"date":"2020-11-30","value":0},{"date":"2020-12-31","value":0},{"date":"2021-01-31","value":0},{"date":"2021-02-28","value":0},{"date":"2021-03-31","value":18},{"date":"2021-06-30","value":487},{"date":"2021-09-30","value":497}],"nb-cycle-aisance-aquatique":[{"date":"2020-12-31","value":98}],"targets":{"nb-cycle-aisance-aquatique":{"target":1387,"target_date":"2022-12-31"},"nb-attestations-savoir-rouler-velo":{"target":3143,"target_date":"2022-12-31"}}},{"dep":"07","libelle":"Ardèche","values":{"nb-attestations-savoir-rouler-velo":{"value":495,"value_date":"2021-09-30"},"nb-cycle-aisance-aquatique":{"value":0,"value_date":"2020-12-31"}},"nb-attestations-savoir-rouler-velo":[{"date":"2017-12-31","value":0},{"date":"2018-12-31","value":0},{"date":"2019-03-31","value":0},{"date":"2019-04-30","value":352},{"date":"2020-11-30","value":359},{"date":"2020-12-31","value":359},{"date":"2021-01-31","value":359},{"date":"2021-02-28","value":364},{"date":"2021-03-31","value":382},{"date":"2021-06-30","value":477},{"date":"2021-09-30","value":495}],"nb-cycle-aisance-aquatique":[{"date":"2020-12-31","value":0}],"targets":{"nb-cycle-aisance-aquatique":{"target":397,"target_date":"2022-12-31"},"nb-attestations-savoir-rouler-velo":{"target":925,"target_date":"2022-12-31"}}},{"dep":"08","libelle":"Ardennes","values":{"nb-attestations-savoir-rouler-velo":{"value":61,"value_date":"2021-09-30"},"nb-cycle-aisance-aquatique":{"value":53,"value_date":"2020-12-31"}},"nb-attestations-savoir-rouler-velo":[{"date":"2017-12-31","value":0},{"date":"2018-12-31","value":0},{"date":"2019-03-31","value":0},{"date":"2019-04-30","value":0},{"date":"2020-11-30","value":60},{"date":"2020-12-31","value":60},{"date":"2021-01-31","value":60},{"date":"2021-02-28","value":60},{"date":"2021-03-31","value":61},{"date":"2021-06-30","value":61},{"date":"2021-09-30","value":61}],"nb-cycle-aisance-aquatique":[{"date":"2020-12-31","value":53}],"targets":{"nb-cycle-aisance-aquatique":{"target":336,"target_date":"2022-12-31"},"nb-attestations-savoir-rouler-velo":{"target":794,"target_date":"2022-12-31"}}},{"dep":"09","libelle":"Ariège","values":{"nb-attestations-savoir-rouler-velo":{"value":104,"value_date":"2021-09-30"},"nb-cycle-aisance-aquatique":{"value":0,"value_date":"2020-12-31"}},"nb-attestations-savoir-rouler-velo":[{"date":"2017-12-31","value":0},{"date":"2018-12-31","value":0},{"date":"2019-03-31","value":0},{"date":"2019-04-30","value":0},{"date":"2020-11-30","value":0},{"date":"2020-12-31","value":0},{"date":"2021-01-31","value":0},{"date":"2021-02-28","value":0},{"date":"2021-03-31","value":0},{"date":"2021-06-30","value":76},{"date":"2021-09-30","value":104}],"nb-cycle-aisance-aquatique":[{"date":"2020-12-31","value":0}],"targets":{"nb-cycle-aisance-aquatique":{"target":168,"target_date":"2022-12-31"},"nb-attestations-savoir-rouler-velo":{"target":393,"target_date":"2022-12-31"}}},{"dep":"10","libelle":"Aube","values":{"nb-attestations-savoir-rouler-velo":{"value":103,"value_date":"2021-09-30"},"nb-cycle-aisance-aquatique":{"value":0,"value_date":"2020-12-31"}},"nb-attestations-savoir-rouler-velo":[{"date":"2017-12-31","value":0},{"date":"2018-12-31","value":0},{"date":"2019-03-31","value":0},{"date":"2019-04-30","value":10},{"date":"2020-11-30","value":10},{"date":"2020-12-31","value":10},{"date":"2021-01-31","value":10},{"date":"2021-02-28","value":10},{"date":"2021-03-31","value":13},{"date":"2021-06-30","value":103},{"date":"2021-09-30","value":103}],"nb-cycle-aisance-aquatique":[{"date":"2020-12-31","value":0}],"targets":{"nb-cycle-aisance-aquatique":{"target":397,"target_date":"2022-12-31"},"nb-attestations-savoir-rouler-velo":{"target":922,"target_date":"2022-12-31"}}},{"dep":"11","libelle":"Aude","values":{"nb-attestations-savoir-rouler-velo":{"value":41,"value_date":"2021-09-30"},"nb-cycle-aisance-aquatique":{"value":0,"value_date":"2020-12-31"}},"nb-attestations-savoir-rouler-velo":[{"date":"2017-12-31","value":0},{"date":"2018-12-31","value":0},{"date":"2019-03-31","value":0},{"date":"2019-04-30","value":0},{"date":"2020-11-30","value":0},{"date":"2020-12-31","value":0},{"date":"2021-01-31","value":0},{"date":"2021-02-28","value":0},{"date":"2021-03-31","value":15},{"date":"2021-06-30","value":24},{"date":"2021-09-30","value":41}],"nb-cycle-aisance-aquatique":[{"date":"2020-12-31","value":0}],"targets":{"nb-cycle-aisance-aquatique":{"target":437,"target_date":"2022-12-31"},"nb-attestations-savoir-rouler-velo":{"target":1028,"target_date":"2022-12-31"}}},{"dep":"12","libelle":"Aveyron","values":{"nb-attestations-savoir-rouler-velo":{"value":318,"value_date":"2021-09-30"},"nb-cycle-aisance-aquatique":{"value":81,"value_date":"2020-12-31"}},"nb-attestations-savoir-rouler-velo":[{"date":"2017-12-31","value":0},{"date":"2018-12-31","value":0},{"date":"2019-03-31","value":0},{"date":"2019-04-30","value":0},{"date":"2020-11-30","value":0},{"date":"2020-12-31","value":0},{"date":"2021-01-31","value":0},{"date":"2021-02-28","value":0},{"date":"2021-03-31","value":4},{"date":"2021-06-30","value":31},{"date":"2021-09-30","value":318}],"nb-cycle-aisance-aquatique":[{"date":"2020-12-31","value":81}],"targets":{"nb-cycle-aisance-aquatique":{"target":304,"target_date":"2022-12-31"},"nb-attestations-savoir-rouler-velo":{"target":717,"target_date":"2022-12-31"}}},{"dep":"13","libelle":"Bouches-du-Rhône","values":{"nb-attestations-savoir-rouler-velo":{"value":193,"value_date":"2021-09-30"},"nb-cycle-aisance-aquatique":{"value":0,"value_date":"2020-12-31"}},"nb-attestations-savoir-rouler-velo":[{"date":"2017-12-31","value":0},{"date":"2018-12-31","value":0},{"date":"2019-03-31","value":0},{"date":"2019-04-30","value":0},{"date":"2020-11-30","value":0},{"date":"2020-12-31","value":0},{"date":"2021-01-31","value":0},{"date":"2021-02-28","value":0},{"date":"2021-03-31","value":66},{"date":"2021-06-30","value":172},{"date":"2021-09-30","value":193}],"nb-cycle-aisance-aquatique":[{"date":"2020-12-31","value":0}],"targets":{"nb-cycle-aisance-aquatique":{"target":2847,"target_date":"2022-12-31"},"nb-attestations-savoir-rouler-velo":{"target":6145,"target_date":"2022-12-31"}}},{"dep":"14","libelle":"Calvados","values":{"nb-attestations-savoir-rouler-velo":{"value":714,"value_date":"2021-09-30"},"nb-cycle-aisance-aquatique":{"value":0,"value_date":"2020-12-31"}},"nb-attestations-savoir-rouler-velo":[{"date":"2017-12-31","value":0},{"date":"2018-12-31","value":0},{"date":"2019-03-31","value":0},{"date":"2019-04-30","value":0},{"date":"2020-11-30","value":31},{"date":"2020-12-31","value":45},{"date":"2021-01-31","value":45},{"date":"2021-02-28","value":55},{"date":"2021-03-31","value":78},{"date":"2021-06-30","value":489},{"date":"2021-09-30","value":714}],"nb-cycle-aisance-aquatique":[{"date":"2020-12-31","value":0}],"targets":{"nb-cycle-aisance-aquatique":{"target":861,"target_date":"2022-12-31"},"nb-attestations-savoir-rouler-velo":{"target":1965,"target_date":"2022-12-31"}}},{"dep":"15","libelle":"Cantal","values":{"nb-attestations-savoir-rouler-velo":{"value":29,"value_date":"2021-09-30"},"nb-cycle-aisance-aquatique":{"value":0,"value_date":"2020-12-31"}},"nb-attestations-savoir-rouler-velo":[{"date":"2017-12-31","value":0},{"date":"2018-12-31","value":0},{"date":"2019-03-31","value":0},{"date":"2019-04-30","value":0},{"date":"2020-11-30","value":0},{"date":"2020-12-31","value":0},{"date":"2021-01-31","value":0},{"date":"2021-02-28","value":0},{"date":"2021-03-31","value":0},{"date":"2021-06-30","value":29},{"date":"2021-09-30","value":29}],"nb-cycle-aisance-aquatique":[{"date":"2020-12-31","value":0}],"targets":{"nb-cycle-aisance-aquatique":{"target":141,"target_date":"2022-12-31"},"nb-attestations-savoir-rouler-velo":{"target":329,"target_date":"2022-12-31"}}},{"dep":"16","libelle":"Charente","values":{"nb-attestations-savoir-rouler-velo":{"value":1464,"value_date":"2021-09-30"},"nb-cycle-aisance-aquatique":{"value":0,"value_date":"2020-12-31"}},"nb-attestations-savoir-rouler-velo":[{"date":"2017-12-31","value":0},{"date":"2018-12-31","value":0},{"date":"2019-03-31","value":0},{"date":"2019-04-30","value":75},{"date":"2020-11-30","value":577},{"date":"2020-12-31","value":602},{"date":"2021-01-31","value":602},{"date":"2021-02-28","value":602},{"date":"2021-03-31","value":604},{"date":"2021-06-30","value":1143},{"date":"2021-09-30","value":1464}],"nb-cycle-aisance-aquatique":[{"date":"2020-12-31","value":0}],"targets":{"nb-cycle-aisance-aquatique":{"target":396,"target_date":"2022-12-31"},"nb-attestations-savoir-rouler-velo":{"target":923,"target_date":"2022-12-31"}}},{"dep":"17","libelle":"Charente-Maritime","values":{"nb-attestations-savoir-rouler-velo":{"value":1481,"value_date":"2021-09-30"},"nb-cycle-aisance-aquatique":{"value":170,"value_date":"2020-12-31"}},"nb-attestations-savoir-rouler-velo":[{"date":"2017-12-31","value":0},{"date":"2018-12-31","value":0},{"date":"2019-03-31","value":0},{"date":"2019-04-30","value":0},{"date":"2020-11-30","value":55},{"date":"2020-12-31","value":55},{"date":"2021-01-31","value":55},{"date":"2021-02-28","value":105},{"date":"2021-03-31","value":162},{"date":"2021-06-30","value":1388},{"date":"2021-09-30","value":1481}],"nb-cycle-aisance-aquatique":[{"date":"2020-12-31","value":170}],"targets":{"nb-cycle-aisance-aquatique":{"target":715,"target_date":"2022-12-31"},"nb-attestations-savoir-rouler-velo":{"target":1666,"target_date":"2022-12-31"}}},{"dep":"18","libelle":"Cher","values":{"nb-attestations-savoir-rouler-velo":{"value":336,"value_date":"2021-09-30"},"nb-cycle-aisance-aquatique":{"value":0,"value_date":"2020-12-31"}},"nb-attestations-savoir-rouler-velo":[{"date":"2017-12-31","value":0},{"date":"2018-12-31","value":0},{"date":"2019-03-31","value":0},{"date":"2019-04-30","value":0},{"date":"2020-11-30","value":16},{"date":"2020-12-31","value":16},{"date":"2021-01-31","value":16},{"date":"2021-02-28","value":16},{"date":"2021-03-31","value":28},{"date":"2021-06-30","value":287},{"date":"2021-09-30","value":336}],"nb-cycle-aisance-aquatique":[{"date":"2020-12-31","value":0}],"targets":{"nb-cycle-aisance-aquatique":{"target":347,"target_date":"2022-12-31"},"nb-attestations-savoir-rouler-velo":{"target":807,"target_date":"2022-12-31"}}},{"dep":"19","libelle":"Corrèze","values":{"nb-attestations-savoir-rouler-velo":{"value":410,"value_date":"2021-09-30"},"nb-cycle-aisance-aquatique":{"value":50,"value_date":"2020-12-31"}},"nb-attestations-savoir-rouler-velo":[{"date":"2017-12-31","value":0},{"date":"2018-12-31","value":0},{"date":"2019-03-31","value":0},{"date":"2019-04-30","value":81},{"date":"2020-11-30","value":81},{"date":"2020-12-31","value":81},{"date":"2021-01-31","value":81},{"date":"2021-02-28","value":81},{"date":"2021-03-31","value":86},{"date":"2021-06-30","value":410},{"date":"2021-09-30","value":410}],"nb-cycle-aisance-aquatique":[{"date":"2020-12-31","value":50}],"targets":{"nb-cycle-aisance-aquatique":{"target":253,"target_date":"2022-12-31"},"nb-attestations-savoir-rouler-velo":{"target":586,"target_date":"2022-12-31"}}},{"dep":"21","libelle":"Côte-d'Or","values":{"nb-attestations-savoir-rouler-velo":{"value":167,"value_date":"2021-09-30"},"nb-cycle-aisance-aquatique":{"value":0,"value_date":"2020-12-31"}},"nb-attestations-savoir-rouler-velo":[{"date":"2017-12-31","value":0},{"date":"2018-12-31","value":0},{"date":"2019-03-31","value":0},{"date":"2019-04-30","value":5},{"date":"2020-11-30","value":5},{"date":"2020-12-31","value":5},{"date":"2021-01-31","value":5},{"date":"2021-02-28","value":5},{"date":"2021-03-31","value":16},{"date":"2021-06-30","value":103},{"date":"2021-09-30","value":167}],"nb-cycle-aisance-aquatique":[{"date":"2020-12-31","value":0}],"targets":{"nb-cycle-aisance-aquatique":{"target":630,"target_date":"2022-12-31"},"nb-attestations-savoir-rouler-velo":{"target":1399,"target_date":"2022-12-31"}}},{"dep":"22","libelle":"Côtes-d'Armor","values":{"nb-attestations-savoir-rouler-velo":{"value":484,"value_date":"2021-09-30"},"nb-cycle-aisance-aquatique":{"value":0,"value_date":"2020-12-31"}},"nb-attestations-savoir-rouler-velo":[{"date":"2017-12-31","value":0},{"date":"2018-12-31","value":0},{"date":"2019-03-31","value":0},{"date":"2019-04-30","value":32},{"date":"2020-11-30","value":78},{"date":"2020-12-31","value":78},{"date":"2021-01-31","value":78},{"date":"2021-02-28","value":78},{"date":"2021-03-31","value":79},{"date":"2021-06-30","value":371},{"date":"2021-09-30","value":484}],"nb-cycle-aisance-aquatique":[{"date":"2020-12-31","value":0}],"targets":{"nb-cycle-aisance-aquatique":{"target":716,"target_date":"2022-12-31"},"nb-attestations-savoir-rouler-velo":{"target":1690,"target_date":"2022-12-31"}}},{"dep":"23","libelle":"Creuse","values":{"nb-attestations-savoir-rouler-velo":{"value":166,"value_date":"2021-09-30"},"nb-cycle-aisance-aquatique":{"value":0,"value_date":"2020-12-31"}},"nb-attestations-savoir-rouler-velo":[{"date":"2017-12-31","value":0},{"date":"2018-12-31","value":0},{"date":"2019-03-31","value":0},{"date":"2019-04-30","value":0},{"date":"2020-11-30","value":0},{"date":"2020-12-31","value":0},{"date":"2021-01-31","value":0},{"date":"2021-02-28","value":0},{"date":"2021-03-31","value":5},{"date":"2021-06-30","value":148},{"date":"2021-09-30","value":166}],"nb-cycle-aisance-aquatique":[{"date":"2020-12-31","value":0}],"targets":{"nb-cycle-aisance-aquatique":{"target":107,"target_date":"2022-12-31"},"nb-attestations-savoir-rouler-velo":{"target":255,"target_date":"2022-12-31"}}},{"dep":"24","libelle":"Dordogne","values":{"nb-attestations-savoir-rouler-velo":{"value":187,"value_date":"2021-09-30"},"nb-cycle-aisance-aquatique":{"value":0,"value_date":"2020-12-31"}},"nb-attestations-savoir-rouler-velo":[{"date":"2017-12-31","value":0},{"date":"2018-12-31","value":0},{"date":"2019-03-31","value":0},{"date":"2019-04-30","value":0},{"date":"2020-11-30","value":50},{"date":"2020-12-31","value":50},{"date":"2021-01-31","value":50},{"date":"2021-02-28","value":50},{"date":"2021-03-31","value":66},{"date":"2021-06-30","value":139},{"date":"2021-09-30","value":187}],"nb-cycle-aisance-aquatique":[{"date":"2020-12-31","value":0}],"targets":{"nb-cycle-aisance-aquatique":{"target":419,"target_date":"2022-12-31"},"nb-attestations-savoir-rouler-velo":{"target":1007,"target_date":"2022-12-31"}}},{"dep":"25","libelle":"Doubs","values":{"nb-attestations-savoir-rouler-velo":{"value":988,"value_date":"2021-09-30"},"nb-cycle-aisance-aquatique":{"value":0,"value_date":"2020-12-31"}},"nb-attestations-savoir-rouler-velo":[{"date":"2017-12-31","value":0},{"date":"2018-12-31","value":0},{"date":"2019-03-31","value":0},{"date":"2019-04-30","value":0},{"date":"2020-11-30","value":61},{"date":"2020-12-31","value":87},{"date":"2021-01-31","value":87},{"date":"2021-02-28","value":87},{"date":"2021-03-31","value":94},{"date":"2021-06-30","value":894},{"date":"2021-09-30","value":988}],"nb-cycle-aisance-aquatique":[{"date":"2020-12-31","value":0}],"targets":{"nb-cycle-aisance-aquatique":{"target":728,"target_date":"2022-12-31"},"nb-attestations-savoir-rouler-velo":{"target":1641,"target_date":"2022-12-31"}}},{"dep":"26","libelle":"Drôme","values":{"nb-attestations-savoir-rouler-velo":{"value":415,"value_date":"2021-09-30"},"nb-cycle-aisance-aquatique":{"value":924,"value_date":"2020-12-31"}},"nb-attestations-savoir-rouler-velo":[{"date":"2017-12-31","value":0},{"date":"2018-12-31","value":0},{"date":"2019-03-31","value":0},{"date":"2019-04-30","value":0},{"date":"2020-11-30","value":0},{"date":"2020-12-31","value":0},{"date":"2021-01-31","value":0},{"date":"2021-02-28","value":0},{"date":"2021-03-31","value":22},{"date":"2021-06-30","value":415},{"date":"2021-09-30","value":415}],"nb-cycle-aisance-aquatique":[{"date":"2020-12-31","value":924}],"targets":{"nb-cycle-aisance-aquatique":{"target":1291,"target_date":"2022-12-31"},"nb-attestations-savoir-rouler-velo":{"target":1585,"target_date":"2022-12-31"}}},{"dep":"27","libelle":"Eure","values":{"nb-attestations-savoir-rouler-velo":{"value":522,"value_date":"2021-09-30"},"nb-cycle-aisance-aquatique":{"value":0,"value_date":"2020-12-31"}},"nb-attestations-savoir-rouler-velo":[{"date":"2017-12-31","value":0},{"date":"2018-12-31","value":0},{"date":"2019-03-31","value":0},{"date":"2019-04-30","value":14},{"date":"2020-11-30","value":41},{"date":"2020-12-31","value":41},{"date":"2021-01-31","value":41},{"date":"2021-02-28","value":41},{"date":"2021-03-31","value":51},{"date":"2021-06-30","value":281},{"date":"2021-09-30","value":522}],"nb-cycle-aisance-aquatique":[{"date":"2020-12-31","value":0}],"targets":{"nb-cycle-aisance-aquatique":{"target":849,"target_date":"2022-12-31"},"nb-attestations-savoir-rouler-velo":{"target":1946,"target_date":"2022-12-31"}}},{"dep":"28","libelle":"Eure-et-Loir","values":{"nb-attestations-savoir-rouler-velo":{"value":840,"value_date":"2021-09-30"},"nb-cycle-aisance-aquatique":{"value":0,"value_date":"2020-12-31"}},"nb-attestations-savoir-rouler-velo":[{"date":"2017-12-31","value":0},{"date":"2018-12-31","value":0},{"date":"2019-03-31","value":0},{"date":"2019-04-30","value":0},{"date":"2020-11-30","value":0},{"date":"2020-12-31","value":0},{"date":"2021-01-31","value":0},{"date":"2021-02-28","value":0},{"date":"2021-03-31","value":5},{"date":"2021-06-30","value":811},{"date":"2021-09-30","value":840}],"nb-cycle-aisance-aquatique":[{"date":"2020-12-31","value":0}],"targets":{"nb-cycle-aisance-aquatique":{"target":604,"target_date":"2022-12-31"},"nb-attestations-savoir-rouler-velo":{"target":1376,"target_date":"2022-12-31"}}},{"dep":"29","libelle":"Finistère","values":{"nb-attestations-savoir-rouler-velo":{"value":651,"value_date":"2021-09-30"},"nb-cycle-aisance-aquatique":{"value":40,"value_date":"2020-12-31"}},"nb-attestations-savoir-rouler-velo":[{"date":"2017-12-31","value":0},{"date":"2018-12-31","value":0},{"date":"2019-03-31","value":0},{"date":"2019-04-30","value":24},{"date":"2020-11-30","value":24},{"date":"2020-12-31","value":24},{"date":"2021-01-31","value":24},{"date":"2021-02-28","value":24},{"date":"2021-03-31","value":55},{"date":"2021-06-30","value":572},{"date":"2021-09-30","value":651}],"nb-cycle-aisance-aquatique":[{"date":"2020-12-31","value":40}],"targets":{"nb-cycle-aisance-aquatique":{"target":1098,"target_date":"2022-12-31"},"nb-attestations-savoir-rouler-velo":{"target":2523,"target_date":"2022-12-31"}}},{"dep":"2A","libelle":"Corse-du-Sud","values":{"nb-attestations-savoir-rouler-velo":{"value":148,"value_date":"2021-09-30"},"nb-cycle-aisance-aquatique":{"value":0,"value_date":"2020-12-31"}},"nb-attestations-savoir-rouler-velo":[{"date":"2017-12-31","value":0},{"date":"2018-12-31","value":0},{"date":"2019-03-31","value":0},{"date":"2019-04-30","value":95},{"date":"2020-11-30","value":95},{"date":"2020-12-31","value":95},{"date":"2021-01-31","value":95},{"date":"2021-02-28","value":95},{"date":"2021-03-31","value":148},{"date":"2021-06-30","value":148},{"date":"2021-09-30","value":148}],"nb-cycle-aisance-aquatique":[{"date":"2020-12-31","value":0}],"targets":{"nb-cycle-aisance-aquatique":{"target":161,"target_date":"2022-12-31"},"nb-attestations-savoir-rouler-velo":{"target":372,"target_date":"2022-12-31"}}},{"dep":"2B","libelle":"Haute-Corse","values":{"nb-attestations-savoir-rouler-velo":{"value":0,"value_date":"2021-09-30"},"nb-cycle-aisance-aquatique":{"value":0,"value_date":"2020-12-31"}},"nb-attestations-savoir-rouler-velo":[{"date":"2017-12-31","value":0},{"date":"2018-12-31","value":0},{"date":"2019-03-31","value":0},{"date":"2019-04-30","value":0},{"date":"2020-11-30","value":0},{"date":"2020-12-31","value":0},{"date":"2021-01-31","value":0},{"date":"2021-02-28","value":0},{"date":"2021-03-31","value":0},{"date":"2021-06-30","value":0},{"date":"2021-09-30","value":0}],"nb-cycle-aisance-aquatique":[{"date":"2020-12-31","value":0}],"targets":{"nb-cycle-aisance-aquatique":{"target":182,"target_date":"2022-12-31"},"nb-attestations-savoir-rouler-velo":{"target":411,"target_date":"2022-12-31"}}},{"dep":"30","libelle":"Gard","values":{"nb-attestations-savoir-rouler-velo":{"value":1320,"value_date":"2021-09-30"},"nb-cycle-aisance-aquatique":{"value":0,"value_date":"2020-12-31"}},"nb-attestations-savoir-rouler-velo":[{"date":"2017-12-31","value":0},{"date":"2018-12-31","value":0},{"date":"2019-03-31","value":0},{"date":"2019-04-30","value":0},{"date":"2020-11-30","value":0},{"date":"2020-12-31","value":0},{"date":"2021-01-31","value":54},{"date":"2021-02-28","value":54},{"date":"2021-03-31","value":331},{"date":"2021-06-30","value":757},{"date":"2021-09-30","value":1320}],"nb-cycle-aisance-aquatique":[{"date":"2020-12-31","value":0}],"targets":{"nb-cycle-aisance-aquatique":{"target":974,"target_date":"2022-12-31"},"nb-attestations-savoir-rouler-velo":{"target":2229,"target_date":"2022-12-31"}}},{"dep":"31","libelle":"Haute-Garonne","values":{"nb-attestations-savoir-rouler-velo":{"value":787,"value_date":"2021-09-30"},"nb-cycle-aisance-aquatique":{"value":0,"value_date":"2020-12-31"}},"nb-attestations-savoir-rouler-velo":[{"date":"2017-12-31","value":0},{"date":"2018-12-31","value":0},{"date":"2019-03-31","value":0},{"date":"2019-04-30","value":34},{"date":"2020-11-30","value":96},{"date":"2020-12-31","value":116},{"date":"2021-01-31","value":116},{"date":"2021-02-28","value":116},{"date":"2021-03-31","value":116},{"date":"2021-06-30","value":269},{"date":"2021-09-30","value":787}],"nb-cycle-aisance-aquatique":[{"date":"2020-12-31","value":0}],"targets":{"nb-cycle-aisance-aquatique":{"target":1823,"target_date":"2022-12-31"},"nb-attestations-savoir-rouler-velo":{"target":3919,"target_date":"2022-12-31"}}},{"dep":"32","libelle":"Gers","values":{"nb-attestations-savoir-rouler-velo":{"value":312,"value_date":"2021-09-30"},"nb-cycle-aisance-aquatique":{"value":24,"value_date":"2020-12-31"}},"nb-attestations-savoir-rouler-velo":[{"date":"2017-12-31","value":0},{"date":"2018-12-31","value":0},{"date":"2019-03-31","value":0},{"date":"2019-04-30","value":0},{"date":"2020-11-30","value":0},{"date":"2020-12-31","value":0},{"date":"2021-01-31","value":0},{"date":"2021-02-28","value":0},{"date":"2021-03-31","value":0},{"date":"2021-06-30","value":102},{"date":"2021-09-30","value":312}],"nb-cycle-aisance-aquatique":[{"date":"2020-12-31","value":24}],"targets":{"nb-cycle-aisance-aquatique":{"target":204,"target_date":"2022-12-31"},"nb-attestations-savoir-rouler-velo":{"target":494,"target_date":"2022-12-31"}}},{"dep":"33","libelle":"Gironde","values":{"nb-attestations-savoir-rouler-velo":{"value":893,"value_date":"2021-09-30"},"nb-cycle-aisance-aquatique":{"value":0,"value_date":"2020-12-31"}},"nb-attestations-savoir-rouler-velo":[{"date":"2017-12-31","value":0},{"date":"2018-12-31","value":0},{"date":"2019-03-31","value":0},{"date":"2019-04-30","value":0},{"date":"2020-11-30","value":0},{"date":"2020-12-31","value":0},{"date":"2021-01-31","value":0},{"date":"2021-02-28","value":0},{"date":"2021-03-31","value":27},{"date":"2021-06-30","value":844},{"date":"2021-09-30","value":893}],"nb-cycle-aisance-aquatique":[{"date":"2020-12-31","value":0}],"targets":{"nb-cycle-aisance-aquatique":{"target":2065,"target_date":"2022-12-31"},"nb-attestations-savoir-rouler-velo":{"target":4549,"target_date":"2022-12-31"}}},{"dep":"34","libelle":"Hérault","values":{"nb-attestations-savoir-rouler-velo":{"value":993,"value_date":"2021-09-30"},"nb-cycle-aisance-aquatique":{"value":0,"value_date":"2020-12-31"}},"nb-attestations-savoir-rouler-velo":[{"date":"2017-12-31","value":0},{"date":"2018-12-31","value":0},{"date":"2019-03-31","value":0},{"date":"2019-04-30","value":350},{"date":"2020-11-30","value":547},{"date":"2020-12-31","value":556},{"date":"2021-01-31","value":614},{"date":"2021-02-28","value":624},{"date":"2021-03-31","value":688},{"date":"2021-06-30","value":919},{"date":"2021-09-30","value":993}],"nb-cycle-aisance-aquatique":[{"date":"2020-12-31","value":0}],"targets":{"nb-cycle-aisance-aquatique":{"target":1496,"target_date":"2022-12-31"},"nb-attestations-savoir-rouler-velo":{"target":3312,"target_date":"2022-12-31"}}},{"dep":"35","libelle":"Ille-et-Vilaine","values":{"nb-attestations-savoir-rouler-velo":{"value":987,"value_date":"2021-09-30"},"nb-cycle-aisance-aquatique":{"value":0,"value_date":"2020-12-31"}},"nb-attestations-savoir-rouler-velo":[{"date":"2017-12-31","value":0},{"date":"2018-12-31","value":0},{"date":"2019-03-31","value":0},{"date":"2019-04-30","value":3},{"date":"2020-11-30","value":221},{"date":"2020-12-31","value":221},{"date":"2021-01-31","value":221},{"date":"2021-02-28","value":221},{"date":"2021-03-31","value":223},{"date":"2021-06-30","value":935},{"date":"2021-09-30","value":987}],"nb-cycle-aisance-aquatique":[{"date":"2020-12-31","value":0}],"targets":{"nb-cycle-aisance-aquatique":{"target":1504,"target_date":"2022-12-31"},"nb-attestations-savoir-rouler-velo":{"target":3359,"target_date":"2022-12-31"}}},{"dep":"36","libelle":"Indre","values":{"nb-attestations-savoir-rouler-velo":{"value":649,"value_date":"2021-09-30"},"nb-cycle-aisance-aquatique":{"value":0,"value_date":"2020-12-31"}},"nb-attestations-savoir-rouler-velo":[{"date":"2017-12-31","value":0},{"date":"2018-12-31","value":0},{"date":"2019-03-31","value":0},{"date":"2019-04-30","value":0},{"date":"2020-11-30","value":0},{"date":"2020-12-31","value":0},{"date":"2021-01-31","value":0},{"date":"2021-02-28","value":0},{"date":"2021-03-31","value":6},{"date":"2021-06-30","value":649},{"date":"2021-09-30","value":649}],"nb-cycle-aisance-aquatique":[{"date":"2020-12-31","value":0}],"targets":{"nb-cycle-aisance-aquatique":{"target":230,"target_date":"2022-12-31"},"nb-attestations-savoir-rouler-velo":{"target":553,"target_date":"2022-12-31"}}},{"dep":"37","libelle":"Indre-et-Loire","values":{"nb-attestations-savoir-rouler-velo":{"value":1373,"value_date":"2021-09-30"},"nb-cycle-aisance-aquatique":{"value":0,"value_date":"2020-12-31"}},"nb-attestations-savoir-rouler-velo":[{"date":"2017-12-31","value":0},{"date":"2018-12-31","value":0},{"date":"2019-03-31","value":0},{"date":"2019-04-30","value":0},{"date":"2020-11-30","value":31},{"date":"2020-12-31","value":89},{"date":"2021-01-31","value":89},{"date":"2021-02-28","value":89},{"date":"2021-03-31","value":114},{"date":"2021-06-30","value":114},{"date":"2021-09-30","value":1373}],"nb-cycle-aisance-aquatique":[{"date":"2020-12-31","value":0}],"targets":{"nb-cycle-aisance-aquatique":{"target":767,"target_date":"2022-12-31"},"nb-attestations-savoir-rouler-velo":{"target":1710,"target_date":"2022-12-31"}}},{"dep":"38","libelle":"Isère","values":{"nb-attestations-savoir-rouler-velo":{"value":2179,"value_date":"2021-09-30"},"nb-cycle-aisance-aquatique":{"value":0,"value_date":"2020-12-31"}},"nb-attestations-savoir-rouler-velo":[{"date":"2017-12-31","value":0},{"date":"2018-12-31","value":0},{"date":"2019-03-31","value":0},{"date":"2019-04-30","value":554},{"date":"2020-11-30","value":790},{"date":"2020-12-31","value":790},{"date":"2021-01-31","value":790},{"date":"2021-02-28","value":790},{"date":"2021-03-31","value":828},{"date":"2021-06-30","value":2004},{"date":"2021-09-30","value":2179}],"nb-cycle-aisance-aquatique":[{"date":"2020-12-31","value":0}],"targets":{"nb-cycle-aisance-aquatique":{"target":1771,"target_date":"2022-12-31"},"nb-attestations-savoir-rouler-velo":{"target":3985,"target_date":"2022-12-31"}}},{"dep":"39","libelle":"Jura","values":{"nb-attestations-savoir-rouler-velo":{"value":4,"value_date":"2021-09-30"},"nb-cycle-aisance-aquatique":{"value":0,"value_date":"2020-12-31"}},"nb-attestations-savoir-rouler-velo":[{"date":"2017-12-31","value":0},{"date":"2018-12-31","value":0},{"date":"2019-03-31","value":0},{"date":"2019-04-30","value":0},{"date":"2020-11-30","value":0},{"date":"2020-12-31","value":0},{"date":"2021-01-31","value":0},{"date":"2021-02-28","value":0},{"date":"2021-03-31","value":4},{"date":"2021-06-30","value":4},{"date":"2021-09-30","value":4}],"nb-cycle-aisance-aquatique":[{"date":"2020-12-31","value":0}],"targets":{"nb-cycle-aisance-aquatique":{"target":313,"target_date":"2022-12-31"},"nb-attestations-savoir-rouler-velo":{"target":730,"target_date":"2022-12-31"}}},{"dep":"40","libelle":"Landes","values":{"nb-attestations-savoir-rouler-velo":{"value":828,"value_date":"2021-09-30"},"nb-cycle-aisance-aquatique":{"value":58,"value_date":"2020-12-31"}},"nb-attestations-savoir-rouler-velo":[{"date":"2017-12-31","value":0},{"date":"2018-12-31","value":0},{"date":"2019-03-31","value":0},{"date":"2019-04-30","value":0},{"date":"2020-11-30","value":8},{"date":"2020-12-31","value":8},{"date":"2021-01-31","value":8},{"date":"2021-02-28","value":20},{"date":"2021-03-31","value":32},{"date":"2021-06-30","value":126},{"date":"2021-09-30","value":828}],"nb-cycle-aisance-aquatique":[{"date":"2020-12-31","value":58}],"targets":{"nb-cycle-aisance-aquatique":{"target":477,"target_date":"2022-12-31"},"nb-attestations-savoir-rouler-velo":{"target":1132,"target_date":"2022-12-31"}}},{"dep":"41","libelle":"Loir-et-Cher","values":{"nb-attestations-savoir-rouler-velo":{"value":1561,"value_date":"2021-09-30"},"nb-cycle-aisance-aquatique":{"value":85,"value_date":"2020-12-31"}},"nb-attestations-savoir-rouler-velo":[{"date":"2017-12-31","value":0},{"date":"2018-12-31","value":0},{"date":"2019-03-31","value":0},{"date":"2019-04-30","value":161},{"date":"2020-11-30","value":372},{"date":"2020-12-31","value":372},{"date":"2021-01-31","value":372},{"date":"2021-02-28","value":372},{"date":"2021-03-31","value":376},{"date":"2021-06-30","value":1519},{"date":"2021-09-30","value":1561}],"nb-cycle-aisance-aquatique":[{"date":"2020-12-31","value":85}],"targets":{"nb-cycle-aisance-aquatique":{"target":403,"target_date":"2022-12-31"},"nb-attestations-savoir-rouler-velo":{"target":959,"target_date":"2022-12-31"}}},{"dep":"42","libelle":"Loire","values":{"nb-attestations-savoir-rouler-velo":{"value":4132,"value_date":"2021-09-30"},"nb-cycle-aisance-aquatique":{"value":0,"value_date":"2020-12-31"}},"nb-attestations-savoir-rouler-velo":[{"date":"2017-12-31","value":0},{"date":"2018-12-31","value":0},{"date":"2019-03-31","value":0},{"date":"2019-04-30","value":40},{"date":"2020-11-30","value":56},{"date":"2020-12-31","value":56},{"date":"2021-01-31","value":56},{"date":"2021-02-28","value":56},{"date":"2021-03-31","value":81},{"date":"2021-06-30","value":3502},{"date":"2021-09-30","value":4132}],"nb-cycle-aisance-aquatique":[{"date":"2020-12-31","value":0}],"targets":{"nb-cycle-aisance-aquatique":{"target":1037,"target_date":"2022-12-31"},"nb-attestations-savoir-rouler-velo":{"target":2285,"target_date":"2022-12-31"}}},{"dep":"43","libelle":"Haute-Loire","values":{"nb-attestations-savoir-rouler-velo":{"value":22,"value_date":"2021-09-30"},"nb-cycle-aisance-aquatique":{"value":0,"value_date":"2020-12-31"}},"nb-attestations-savoir-rouler-velo":[{"date":"2017-12-31","value":0},{"date":"2018-12-31","value":0},{"date":"2019-03-31","value":0},{"date":"2019-04-30","value":0},{"date":"2020-11-30","value":0},{"date":"2020-12-31","value":0},{"date":"2021-01-31","value":0},{"date":"2021-02-28","value":0},{"date":"2021-03-31","value":6},{"date":"2021-06-30","value":22},{"date":"2021-09-30","value":22}],"nb-cycle-aisance-aquatique":[{"date":"2020-12-31","value":0}],"targets":{"nb-cycle-aisance-aquatique":{"target":276,"target_date":"2022-12-31"},"nb-attestations-savoir-rouler-velo":{"target":625,"target_date":"2022-12-31"}}},{"dep":"44","libelle":"Loire-Atlantique","values":{"nb-attestations-savoir-rouler-velo":{"value":817,"value_date":"2021-09-30"},"nb-cycle-aisance-aquatique":{"value":0,"value_date":"2020-12-31"}},"nb-attestations-savoir-rouler-velo":[{"date":"2017-12-31","value":0},{"date":"2018-12-31","value":0},{"date":"2019-03-31","value":0},{"date":"2019-04-30","value":328},{"date":"2020-11-30","value":467},{"date":"2020-12-31","value":467},{"date":"2021-01-31","value":467},{"date":"2021-02-28","value":479},{"date":"2021-03-31","value":488},{"date":"2021-06-30","value":665},{"date":"2021-09-30","value":817}],"nb-cycle-aisance-aquatique":[{"date":"2020-12-31","value":0}],"targets":{"nb-cycle-aisance-aquatique":{"target":1995,"target_date":"2022-12-31"},"nb-attestations-savoir-rouler-velo":{"target":4453,"target_date":"2022-12-31"}}},{"dep":"45","libelle":"Loiret","values":{"nb-attestations-savoir-rouler-velo":{"value":242,"value_date":"2021-09-30"},"nb-cycle-aisance-aquatique":{"value":0,"value_date":"2020-12-31"}},"nb-attestations-savoir-rouler-velo":[{"date":"2017-12-31","value":0},{"date":"2018-12-31","value":0},{"date":"2019-03-31","value":0},{"date":"2019-04-30","value":0},{"date":"2020-11-30","value":8},{"date":"2020-12-31","value":8},{"date":"2021-01-31","value":8},{"date":"2021-02-28","value":49},{"date":"2021-03-31","value":64},{"date":"2021-06-30","value":212},{"date":"2021-09-30","value":242}],"nb-cycle-aisance-aquatique":[{"date":"2020-12-31","value":0}],"targets":{"nb-cycle-aisance-aquatique":{"target":950,"target_date":"2022-12-31"},"nb-attestations-savoir-rouler-velo":{"target":2149,"target_date":"2022-12-31"}}},{"dep":"46","libelle":"Lot","values":{"nb-attestations-savoir-rouler-velo":{"value":151,"value_date":"2021-09-30"},"nb-cycle-aisance-aquatique":{"value":0,"value_date":"2020-12-31"}},"nb-attestations-savoir-rouler-velo":[{"date":"2017-12-31","value":0},{"date":"2018-12-31","value":0},{"date":"2019-03-31","value":0},{"date":"2019-04-30","value":0},{"date":"2020-11-30","value":0},{"date":"2020-12-31","value":0},{"date":"2021-01-31","value":0},{"date":"2021-02-28","value":0},{"date":"2021-03-31","value":151},{"date":"2021-06-30","value":151},{"date":"2021-09-30","value":151}],"nb-cycle-aisance-aquatique":[{"date":"2020-12-31","value":0}],"targets":{"nb-cycle-aisance-aquatique":{"target":168,"target_date":"2022-12-31"},"nb-attestations-savoir-rouler-velo":{"target":416,"target_date":"2022-12-31"}}},{"dep":"47","libelle":"Lot-et-Garonne","values":{"nb-attestations-savoir-rouler-velo":{"value":330,"value_date":"2021-09-30"},"nb-cycle-aisance-aquatique":{"value":95,"value_date":"2020-12-31"}},"nb-attestations-savoir-rouler-velo":[{"date":"2017-12-31","value":0},{"date":"2018-12-31","value":0},{"date":"2019-03-31","value":0},{"date":"2019-04-30","value":0},{"date":"2020-11-30","value":24},{"date":"2020-12-31","value":24},{"date":"2021-01-31","value":33},{"date":"2021-02-28","value":35},{"date":"2021-03-31","value":117},{"date":"2021-06-30","value":198},{"date":"2021-09-30","value":330}],"nb-cycle-aisance-aquatique":[{"date":"2020-12-31","value":95}],"targets":{"nb-cycle-aisance-aquatique":{"target":387,"target_date":"2022-12-31"},"nb-attestations-savoir-rouler-velo":{"target":901,"target_date":"2022-12-31"}}},{"dep":"48","libelle":"Lozère","values":{"nb-attestations-savoir-rouler-velo":{"value":188,"value_date":"2021-09-30"},"nb-cycle-aisance-aquatique":{"value":0,"value_date":"2020-12-31"}},"nb-attestations-savoir-rouler-velo":[{"date":"2017-12-31","value":0},{"date":"2018-12-31","value":0},{"date":"2019-03-31","value":0},{"date":"2019-04-30","value":0},{"date":"2020-11-30","value":69},{"date":"2020-12-31","value":104},{"date":"2021-01-31","value":104},{"date":"2021-02-28","value":104},{"date":"2021-03-31","value":188},{"date":"2021-06-30","value":188},{"date":"2021-09-30","value":188}],"nb-cycle-aisance-aquatique":[{"date":"2020-12-31","value":0}],"targets":{"nb-cycle-aisance-aquatique":{"target":86,"target_date":"2022-12-31"},"nb-attestations-savoir-rouler-velo":{"target":199,"target_date":"2022-12-31"}}},{"dep":"49","libelle":"Maine-et-Loire","values":{"nb-attestations-savoir-rouler-velo":{"value":615,"value_date":"2021-09-30"},"nb-cycle-aisance-aquatique":{"value":0,"value_date":"2020-12-31"}},"nb-attestations-savoir-rouler-velo":[{"date":"2017-12-31","value":0},{"date":"2018-12-31","value":0},{"date":"2019-03-31","value":0},{"date":"2019-04-30","value":0},{"date":"2020-11-30","value":0},{"date":"2020-12-31","value":0},{"date":"2021-01-31","value":0},{"date":"2021-02-28","value":59},{"date":"2021-03-31","value":66},{"date":"2021-06-30","value":463},{"date":"2021-09-30","value":615}],"nb-cycle-aisance-aquatique":[{"date":"2020-12-31","value":0}],"targets":{"nb-cycle-aisance-aquatique":{"target":1140,"target_date":"2022-12-31"},"nb-attestations-savoir-rouler-velo":{"target":2579,"target_date":"2022-12-31"}}},{"dep":"50","libelle":"Manche","values":{"nb-attestations-savoir-rouler-velo":{"value":1877,"value_date":"2021-09-30"},"nb-cycle-aisance-aquatique":{"value":0,"value_date":"2020-12-31"}},"nb-attestations-savoir-rouler-velo":[{"date":"2017-12-31","value":0},{"date":"2018-12-31","value":0},{"date":"2019-03-31","value":0},{"date":"2019-04-30","value":0},{"date":"2020-11-30","value":24},{"date":"2020-12-31","value":24},{"date":"2021-01-31","value":24},{"date":"2021-02-28","value":24},{"date":"2021-03-31","value":27},{"date":"2021-06-30","value":491},{"date":"2021-09-30","value":1877}],"nb-cycle-aisance-aquatique":[{"date":"2020-12-31","value":0}],"targets":{"nb-cycle-aisance-aquatique":{"target":588,"target_date":"2022-12-31"},"nb-attestations-savoir-rouler-velo":{"target":1345,"target_date":"2022-12-31"}}},{"dep":"51","libelle":"Marne","values":{"nb-attestations-savoir-rouler-velo":{"value":474,"value_date":"2021-09-30"},"nb-cycle-aisance-aquatique":{"value":248,"value_date":"2020-12-31"}},"nb-attestations-savoir-rouler-velo":[{"date":"2017-12-31","value":0},{"date":"2018-12-31","value":0},{"date":"2019-03-31","value":0},{"date":"2019-04-30","value":0},{"date":"2020-11-30","value":170},{"date":"2020-12-31","value":170},{"date":"2021-01-31","value":170},{"date":"2021-02-28","value":170},{"date":"2021-03-31","value":185},{"date":"2021-06-30","value":474},{"date":"2021-09-30","value":474}],"nb-cycle-aisance-aquatique":[{"date":"2020-12-31","value":248}],"targets":{"nb-cycle-aisance-aquatique":{"target":741,"target_date":"2022-12-31"},"nb-attestations-savoir-rouler-velo":{"target":1639,"target_date":"2022-12-31"}}},{"dep":"52","libelle":"Haute-Marne","values":{"nb-attestations-savoir-rouler-velo":{"value":1675,"value_date":"2021-09-30"},"nb-cycle-aisance-aquatique":{"value":0,"value_date":"2020-12-31"}},"nb-attestations-savoir-rouler-velo":[{"date":"2017-12-31","value":0},{"date":"2018-12-31","value":0},{"date":"2019-03-31","value":0},{"date":"2019-04-30","value":0},{"date":"2020-11-30","value":400},{"date":"2020-12-31","value":400},{"date":"2021-01-31","value":400},{"date":"2021-02-28","value":400},{"date":"2021-03-31","value":406},{"date":"2021-06-30","value":1434},{"date":"2021-09-30","value":1675}],"nb-cycle-aisance-aquatique":[{"date":"2020-12-31","value":0}],"targets":{"nb-cycle-aisance-aquatique":{"target":197,"target_date":"2022-12-31"},"nb-attestations-savoir-rouler-velo":{"target":450,"target_date":"2022-12-31"}}},{"dep":"53","libelle":"Mayenne","values":{"nb-attestations-savoir-rouler-velo":{"value":817,"value_date":"2021-09-30"},"nb-cycle-aisance-aquatique":{"value":0,"value_date":"2020-12-31"}},"nb-attestations-savoir-rouler-velo":[{"date":"2017-12-31","value":0},{"date":"2018-12-31","value":0},{"date":"2019-03-31","value":0},{"date":"2019-04-30","value":0},{"date":"2020-11-30","value":0},{"date":"2020-12-31","value":0},{"date":"2021-01-31","value":0},{"date":"2021-02-28","value":0},{"date":"2021-03-31","value":8},{"date":"2021-06-30","value":525},{"date":"2021-09-30","value":817}],"nb-cycle-aisance-aquatique":[{"date":"2020-12-31","value":0}],"targets":{"nb-cycle-aisance-aquatique":{"target":411,"target_date":"2022-12-31"},"nb-attestations-savoir-rouler-velo":{"target":947,"target_date":"2022-12-31"}}},{"dep":"54","libelle":"Meurthe-et-Moselle","values":{"nb-attestations-savoir-rouler-velo":{"value":485,"value_date":"2021-09-30"},"nb-cycle-aisance-aquatique":{"value":41,"value_date":"2020-12-31"}},"nb-attestations-savoir-rouler-velo":[{"date":"2017-12-31","value":0},{"date":"2018-12-31","value":0},{"date":"2019-03-31","value":0},{"date":"2019-04-30","value":0},{"date":"2020-11-30","value":457},{"date":"2020-12-31","value":469},{"date":"2021-01-31","value":469},{"date":"2021-02-28","value":469},{"date":"2021-03-31","value":485},{"date":"2021-06-30","value":485},{"date":"2021-09-30","value":485}],"nb-cycle-aisance-aquatique":[{"date":"2020-12-31","value":41}],"targets":{"nb-cycle-aisance-aquatique":{"target":896,"target_date":"2022-12-31"},"nb-attestations-savoir-rouler-velo":{"target":2007,"target_date":"2022-12-31"}}},{"dep":"55","libelle":"Meuse","values":{"nb-attestations-savoir-rouler-velo":{"value":465,"value_date":"2021-09-30"},"nb-cycle-aisance-aquatique":{"value":335,"value_date":"2020-12-31"}},"nb-attestations-savoir-rouler-velo":[{"date":"2017-12-31","value":0},{"date":"2018-12-31","value":0},{"date":"2019-03-31","value":0},{"date":"2019-04-30","value":0},{"date":"2020-11-30","value":0},{"date":"2020-12-31","value":0},{"date":"2021-01-31","value":0},{"date":"2021-02-28","value":0},{"date":"2021-03-31","value":1},{"date":"2021-06-30","value":42},{"date":"2021-09-30","value":465}],"nb-cycle-aisance-aquatique":[{"date":"2020-12-31","value":335}],"targets":{"nb-cycle-aisance-aquatique":{"target":718,"target_date":"2022-12-31"},"nb-attestations-savoir-rouler-velo":{"target":482,"target_date":"2022-12-31"}}},{"dep":"56","libelle":"Morbihan","values":{"nb-attestations-savoir-rouler-velo":{"value":1189,"value_date":"2021-09-30"},"nb-cycle-aisance-aquatique":{"value":0,"value_date":"2020-12-31"}},"nb-attestations-savoir-rouler-velo":[{"date":"2017-12-31","value":0},{"date":"2018-12-31","value":0},{"date":"2019-03-31","value":0},{"date":"2019-04-30","value":146},{"date":"2020-11-30","value":146},{"date":"2020-12-31","value":146},{"date":"2021-01-31","value":171},{"date":"2021-02-28","value":171},{"date":"2021-03-31","value":187},{"date":"2021-06-30","value":837},{"date":"2021-09-30","value":1189}],"nb-cycle-aisance-aquatique":[{"date":"2020-12-31","value":0}],"targets":{"nb-cycle-aisance-aquatique":{"target":951,"target_date":"2022-12-31"},"nb-attestations-savoir-rouler-velo":{"target":2206,"target_date":"2022-12-31"}}},{"dep":"57","libelle":"Moselle","values":{"nb-attestations-savoir-rouler-velo":{"value":321,"value_date":"2021-09-30"},"nb-cycle-aisance-aquatique":{"value":73,"value_date":"2020-12-31"}},"nb-attestations-savoir-rouler-velo":[{"date":"2017-12-31","value":0},{"date":"2018-12-31","value":0},{"date":"2019-03-31","value":0},{"date":"2019-04-30","value":9},{"date":"2020-11-30","value":10},{"date":"2020-12-31","value":22},{"date":"2021-01-31","value":22},{"date":"2021-02-28","value":22},{"date":"2021-03-31","value":36},{"date":"2021-06-30","value":87},{"date":"2021-09-30","value":321}],"nb-cycle-aisance-aquatique":[{"date":"2020-12-31","value":73}],"targets":{"nb-cycle-aisance-aquatique":{"target":1293,"target_date":"2022-12-31"},"nb-attestations-savoir-rouler-velo":{"target":2837,"target_date":"2022-12-31"}}},{"dep":"58","libelle":"Nièvre","values":{"nb-attestations-savoir-rouler-velo":{"value":1030,"value_date":"2021-09-30"},"nb-cycle-aisance-aquatique":{"value":0,"value_date":"2020-12-31"}},"nb-attestations-savoir-rouler-velo":[{"date":"2017-12-31","value":0},{"date":"2018-12-31","value":0},{"date":"2019-03-31","value":0},{"date":"2019-04-30","value":98},{"date":"2020-11-30","value":117},{"date":"2020-12-31","value":117},{"date":"2021-01-31","value":117},{"date":"2021-02-28","value":117},{"date":"2021-03-31","value":122},{"date":"2021-06-30","value":1030},{"date":"2021-09-30","value":1030}],"nb-cycle-aisance-aquatique":[{"date":"2020-12-31","value":0}],"targets":{"nb-cycle-aisance-aquatique":{"target":211,"target_date":"2022-12-31"},"nb-attestations-savoir-rouler-velo":{"target":476,"target_date":"2022-12-31"}}},{"dep":"59","libelle":"Nord","values":{"nb-attestations-savoir-rouler-velo":{"value":754,"value_date":"2021-09-30"},"nb-cycle-aisance-aquatique":{"value":0,"value_date":"2020-12-31"}},"nb-attestations-savoir-rouler-velo":[{"date":"2017-12-31","value":0},{"date":"2018-12-31","value":0},{"date":"2019-03-31","value":0},{"date":"2019-04-30","value":100},{"date":"2020-11-30","value":656},{"date":"2020-12-31","value":656},{"date":"2021-01-31","value":665},{"date":"2021-02-28","value":686},{"date":"2021-03-31","value":754},{"date":"2021-06-30","value":754},{"date":"2021-09-30","value":754}],"nb-cycle-aisance-aquatique":[{"date":"2020-12-31","value":0}],"targets":{"nb-cycle-aisance-aquatique":{"target":2351,"target_date":"2022-12-31"},"nb-attestations-savoir-rouler-velo":{"target":8208,"target_date":"2022-12-31"}}},{"dep":"60","libelle":"Oise","values":{"nb-attestations-savoir-rouler-velo":{"value":276,"value_date":"2021-09-30"},"nb-cycle-aisance-aquatique":{"value":54,"value_date":"2020-12-31"}},"nb-attestations-savoir-rouler-velo":[{"date":"2017-12-31","value":0},{"date":"2018-12-31","value":0},{"date":"2019-03-31","value":0},{"date":"2019-04-30","value":40},{"date":"2020-11-30","value":149},{"date":"2020-12-31","value":149},{"date":"2021-01-31","value":149},{"date":"2021-02-28","value":149},{"date":"2021-03-31","value":173},{"date":"2021-06-30","value":224},{"date":"2021-09-30","value":276}],"nb-cycle-aisance-aquatique":[{"date":"2020-12-31","value":54}],"targets":{"nb-cycle-aisance-aquatique":{"target":1200,"target_date":"2022-12-31"},"nb-attestations-savoir-rouler-velo":{"target":2688,"target_date":"2022-12-31"}}},{"dep":"61","libelle":"Orne","values":{"nb-attestations-savoir-rouler-velo":{"value":76,"value_date":"2021-09-30"},"nb-cycle-aisance-aquatique":{"value":0,"value_date":"2020-12-31"}},"nb-attestations-savoir-rouler-velo":[{"date":"2017-12-31","value":0},{"date":"2018-12-31","value":0},{"date":"2019-03-31","value":0},{"date":"2019-04-30","value":0},{"date":"2020-11-30","value":31},{"date":"2020-12-31","value":31},{"date":"2021-01-31","value":31},{"date":"2021-02-28","value":43},{"date":"2021-03-31","value":59},{"date":"2021-06-30","value":70},{"date":"2021-09-30","value":76}],"nb-cycle-aisance-aquatique":[{"date":"2020-12-31","value":0}],"targets":{"nb-cycle-aisance-aquatique":{"target":325,"target_date":"2022-12-31"},"nb-attestations-savoir-rouler-velo":{"target":746,"target_date":"2022-12-31"}}},{"dep":"62","libelle":"Pas-de-Calais","values":{"nb-attestations-savoir-rouler-velo":{"value":1594,"value_date":"2021-09-30"},"nb-cycle-aisance-aquatique":{"value":10,"value_date":"2020-12-31"}},"nb-attestations-savoir-rouler-velo":[{"date":"2017-12-31","value":0},{"date":"2018-12-31","value":0},{"date":"2019-03-31","value":0},{"date":"2019-04-30","value":44},{"date":"2020-11-30","value":167},{"date":"2020-12-31","value":188},{"date":"2021-01-31","value":190},{"date":"2021-02-28","value":200},{"date":"2021-03-31","value":663},{"date":"2021-06-30","value":921},{"date":"2021-09-30","value":1594}],"nb-cycle-aisance-aquatique":[{"date":"2020-12-31","value":10}],"targets":{"nb-cycle-aisance-aquatique":{"target":2086,"target_date":"2022-12-31"},"nb-attestations-savoir-rouler-velo":{"target":4627,"target_date":"2022-12-31"}}},{"dep":"63","libelle":"Puy-de-Dôme","values":{"nb-attestations-savoir-rouler-velo":{"value":441,"value_date":"2021-09-30"},"nb-cycle-aisance-aquatique":{"value":128,"value_date":"2020-12-31"}},"nb-attestations-savoir-rouler-velo":[{"date":"2017-12-31","value":0},{"date":"2018-12-31","value":0},{"date":"2019-03-31","value":0},{"date":"2019-04-30","value":96},{"date":"2020-11-30","value":97},{"date":"2020-12-31","value":97},{"date":"2021-01-31","value":97},{"date":"2021-02-28","value":97},{"date":"2021-03-31","value":100},{"date":"2021-06-30","value":290},{"date":"2021-09-30","value":441}],"nb-cycle-aisance-aquatique":[{"date":"2020-12-31","value":128}],"targets":{"nb-cycle-aisance-aquatique":{"target":773,"target_date":"2022-12-31"},"nb-attestations-savoir-rouler-velo":{"target":1731,"target_date":"2022-12-31"}}},{"dep":"64","libelle":"Pyrénées-Atlantiques","values":{"nb-attestations-savoir-rouler-velo":{"value":1042,"value_date":"2021-09-30"},"nb-cycle-aisance-aquatique":{"value":35,"value_date":"2020-12-31"}},"nb-attestations-savoir-rouler-velo":[{"date":"2017-12-31","value":0},{"date":"2018-12-31","value":0},{"date":"2019-03-31","value":0},{"date":"2019-04-30","value":0},{"date":"2020-11-30","value":534},{"date":"2020-12-31","value":534},{"date":"2021-01-31","value":534},{"date":"2021-02-28","value":534},{"date":"2021-03-31","value":548},{"date":"2021-06-30","value":960},{"date":"2021-09-30","value":1042}],"nb-cycle-aisance-aquatique":[{"date":"2020-12-31","value":35}],"targets":{"nb-cycle-aisance-aquatique":{"target":789,"target_date":"2022-12-31"},"nb-attestations-savoir-rouler-velo":{"target":1777,"target_date":"2022-12-31"}}},{"dep":"65","libelle":"Hautes-Pyrénées","values":{"nb-attestations-savoir-rouler-velo":{"value":146,"value_date":"2021-09-30"},"nb-cycle-aisance-aquatique":{"value":1054,"value_date":"2020-12-31"}},"nb-attestations-savoir-rouler-velo":[{"date":"2017-12-31","value":0},{"date":"2018-12-31","value":0},{"date":"2019-03-31","value":0},{"date":"2019-04-30","value":0},{"date":"2020-11-30","value":30},{"date":"2020-12-31","value":30},{"date":"2021-01-31","value":30},{"date":"2021-02-28","value":30},{"date":"2021-03-31","value":35},{"date":"2021-06-30","value":121},{"date":"2021-09-30","value":146}],"nb-cycle-aisance-aquatique":[{"date":"2020-12-31","value":1054}],"targets":{"nb-cycle-aisance-aquatique":{"target":1746,"target_date":"2022-12-31"},"nb-attestations-savoir-rouler-velo":{"target":556,"target_date":"2022-12-31"}}},{"dep":"66","libelle":"Pyrénées-Orientales","values":{"nb-attestations-savoir-rouler-velo":{"value":529,"value_date":"2021-09-30"},"nb-cycle-aisance-aquatique":{"value":0,"value_date":"2020-12-31"}},"nb-attestations-savoir-rouler-velo":[{"date":"2017-12-31","value":0},{"date":"2018-12-31","value":0},{"date":"2019-03-31","value":0},{"date":"2019-04-30","value":0},{"date":"2020-11-30","value":7},{"date":"2020-12-31","value":7},{"date":"2021-01-31","value":7},{"date":"2021-02-28","value":7},{"date":"2021-03-31","value":74},{"date":"2021-06-30","value":413},{"date":"2021-09-30","value":529}],"nb-cycle-aisance-aquatique":[{"date":"2020-12-31","value":0}],"targets":{"nb-cycle-aisance-aquatique":{"target":590,"target_date":"2022-12-31"},"nb-attestations-savoir-rouler-velo":{"target":1334,"target_date":"2022-12-31"}}},{"dep":"67","libelle":"Bas-Rhin","values":{"nb-attestations-savoir-rouler-velo":{"value":643,"value_date":"2021-09-30"},"nb-cycle-aisance-aquatique":{"value":48,"value_date":"2020-12-31"}},"nb-attestations-savoir-rouler-velo":[{"date":"2017-12-31","value":0},{"date":"2018-12-31","value":0},{"date":"2019-03-31","value":0},{"date":"2019-04-30","value":0},{"date":"2020-11-30","value":30},{"date":"2020-12-31","value":30},{"date":"2021-01-31","value":30},{"date":"2021-02-28","value":30},{"date":"2021-03-31","value":58},{"date":"2021-06-30","value":492},{"date":"2021-09-30","value":643}],"nb-cycle-aisance-aquatique":[{"date":"2020-12-31","value":48}],"targets":{"nb-cycle-aisance-aquatique":{"target":1425,"target_date":"2022-12-31"},"nb-attestations-savoir-rouler-velo":{"target":3192,"target_date":"2022-12-31"}}},{"dep":"68","libelle":"Haut-Rhin","values":{"nb-attestations-savoir-rouler-velo":{"value":253,"value_date":"2021-09-30"},"nb-cycle-aisance-aquatique":{"value":36,"value_date":"2020-12-31"}},"nb-attestations-savoir-rouler-velo":[{"date":"2017-12-31","value":0},{"date":"2018-12-31","value":0},{"date":"2019-03-31","value":0},{"date":"2019-04-30","value":0},{"date":"2020-11-30","value":0},{"date":"2020-12-31","value":0},{"date":"2021-01-31","value":0},{"date":"2021-02-28","value":0},{"date":"2021-03-31","value":0},{"date":"2021-06-30","value":205},{"date":"2021-09-30","value":253}],"nb-cycle-aisance-aquatique":[{"date":"2020-12-31","value":36}],"targets":{"nb-cycle-aisance-aquatique":{"target":988,"target_date":"2022-12-31"},"nb-attestations-savoir-rouler-velo":{"target":2188,"target_date":"2022-12-31"}}},{"dep":"69","libelle":"Rhône","values":{"nb-attestations-savoir-rouler-velo":{"value":604,"value_date":"2021-09-30"},"nb-cycle-aisance-aquatique":{"value":0,"value_date":"2020-12-31"}},"nb-attestations-savoir-rouler-velo":[{"date":"2017-12-31","value":0},{"date":"2018-12-31","value":0},{"date":"2019-03-31","value":0},{"date":"2019-04-30","value":0},{"date":"2020-11-30","value":35},{"date":"2020-12-31","value":40},{"date":"2021-01-31","value":40},{"date":"2021-02-28","value":40},{"date":"2021-03-31","value":49},{"date":"2021-06-30","value":375},{"date":"2021-09-30","value":604}],"nb-cycle-aisance-aquatique":[{"date":"2020-12-31","value":0}],"targets":{"nb-cycle-aisance-aquatique":{"target":2278,"target_date":"2022-12-31"},"nb-attestations-savoir-rouler-velo":{"target":5788,"target_date":"2022-12-31"}}},{"dep":"70","libelle":"Haute-Saône","values":{"nb-attestations-savoir-rouler-velo":{"value":144,"value_date":"2021-09-30"},"nb-cycle-aisance-aquatique":{"value":0,"value_date":"2020-12-31"}},"nb-attestations-savoir-rouler-velo":[{"date":"2017-12-31","value":0},{"date":"2018-12-31","value":0},{"date":"2019-03-31","value":0},{"date":"2019-04-30","value":0},{"date":"2020-11-30","value":0},{"date":"2020-12-31","value":0},{"date":"2021-01-31","value":0},{"date":"2021-02-28","value":0},{"date":"2021-03-31","value":15},{"date":"2021-06-30","value":21},{"date":"2021-09-30","value":144}],"nb-cycle-aisance-aquatique":[{"date":"2020-12-31","value":0}],"targets":{"nb-cycle-aisance-aquatique":{"target":287,"target_date":"2022-12-31"},"nb-attestations-savoir-rouler-velo":{"target":665,"target_date":"2022-12-31"}}},{"dep":"71","libelle":"Saône-et-Loire","values":{"nb-attestations-savoir-rouler-velo":{"value":114,"value_date":"2021-09-30"},"nb-cycle-aisance-aquatique":{"value":0,"value_date":"2020-12-31"}},"nb-attestations-savoir-rouler-velo":[{"date":"2017-12-31","value":0},{"date":"2018-12-31","value":0},{"date":"2019-03-31","value":0},{"date":"2019-04-30","value":24},{"date":"2020-11-30","value":54},{"date":"2020-12-31","value":54},{"date":"2021-01-31","value":54},{"date":"2021-02-28","value":57},{"date":"2021-03-31","value":69},{"date":"2021-06-30","value":114},{"date":"2021-09-30","value":114}],"nb-cycle-aisance-aquatique":[{"date":"2020-12-31","value":0}],"targets":{"nb-cycle-aisance-aquatique":{"target":646,"target_date":"2022-12-31"},"nb-attestations-savoir-rouler-velo":{"target":1453,"target_date":"2022-12-31"}}},{"dep":"72","libelle":"Sarthe","values":{"nb-attestations-savoir-rouler-velo":{"value":258,"value_date":"2021-09-30"},"nb-cycle-aisance-aquatique":{"value":0,"value_date":"2020-12-31"}},"nb-attestations-savoir-rouler-velo":[{"date":"2017-12-31","value":0},{"date":"2018-12-31","value":0},{"date":"2019-03-31","value":0},{"date":"2019-04-30","value":0},{"date":"2020-11-30","value":0},{"date":"2020-12-31","value":0},{"date":"2021-01-31","value":0},{"date":"2021-02-28","value":0},{"date":"2021-03-31","value":6},{"date":"2021-06-30","value":258},{"date":"2021-09-30","value":258}],"nb-cycle-aisance-aquatique":[{"date":"2020-12-31","value":0}],"targets":{"nb-cycle-aisance-aquatique":{"target":747,"target_date":"2022-12-31"},"nb-attestations-savoir-rouler-velo":{"target":1697,"target_date":"2022-12-31"}}},{"dep":"73","libelle":"Savoie","values":{"nb-attestations-savoir-rouler-velo":{"value":412,"value_date":"2021-09-30"},"nb-cycle-aisance-aquatique":{"value":0,"value_date":"2020-12-31"}},"nb-attestations-savoir-rouler-velo":[{"date":"2017-12-31","value":0},{"date":"2018-12-31","value":0},{"date":"2019-03-31","value":0},{"date":"2019-04-30","value":12},{"date":"2020-11-30","value":12},{"date":"2020-12-31","value":12},{"date":"2021-01-31","value":12},{"date":"2021-02-28","value":12},{"date":"2021-03-31","value":24},{"date":"2021-06-30","value":192},{"date":"2021-09-30","value":412}],"nb-cycle-aisance-aquatique":[{"date":"2020-12-31","value":0}],"targets":{"nb-cycle-aisance-aquatique":{"target":544,"target_date":"2022-12-31"},"nb-attestations-savoir-rouler-velo":{"target":1222,"target_date":"2022-12-31"}}},{"dep":"74","libelle":"Haute-Savoie","values":{"nb-attestations-savoir-rouler-velo":{"value":1398,"value_date":"2021-09-30"},"nb-cycle-aisance-aquatique":{"value":180,"value_date":"2020-12-31"}},"nb-attestations-savoir-rouler-velo":[{"date":"2017-12-31","value":0},{"date":"2018-12-31","value":0},{"date":"2019-03-31","value":0},{"date":"2019-04-30","value":102},{"date":"2020-11-30","value":353},{"date":"2020-12-31","value":353},{"date":"2021-01-31","value":353},{"date":"2021-02-28","value":353},{"date":"2021-03-31","value":481},{"date":"2021-06-30","value":725},{"date":"2021-09-30","value":1398}],"nb-cycle-aisance-aquatique":[{"date":"2020-12-31","value":180}],"targets":{"nb-cycle-aisance-aquatique":{"target":1164,"target_date":"2022-12-31"},"nb-attestations-savoir-rouler-velo":{"target":2509,"target_date":"2022-12-31"}}},{"dep":"75","libelle":"Paris","values":{"nb-attestations-savoir-rouler-velo":{"value":591,"value_date":"2021-09-30"},"nb-cycle-aisance-aquatique":{"value":0,"value_date":"2020-12-31"}},"nb-attestations-savoir-rouler-velo":[{"date":"2017-12-31","value":0},{"date":"2018-12-31","value":0},{"date":"2019-03-31","value":0},{"date":"2019-04-30","value":56},{"date":"2020-11-30","value":378},{"date":"2020-12-31","value":413},{"date":"2021-01-31","value":413},{"date":"2021-02-28","value":413},{"date":"2021-03-31","value":489},{"date":"2021-06-30","value":591},{"date":"2021-09-30","value":591}],"nb-cycle-aisance-aquatique":[{"date":"2020-12-31","value":0}],"targets":{"nb-cycle-aisance-aquatique":{"target":2194,"target_date":"2022-12-31"},"nb-attestations-savoir-rouler-velo":{"target":4921,"target_date":"2022-12-31"}}},{"dep":"76","libelle":"Seine-Maritime","values":{"nb-attestations-savoir-rouler-velo":{"value":241,"value_date":"2021-09-30"},"nb-cycle-aisance-aquatique":{"value":0,"value_date":"2020-12-31"}},"nb-attestations-savoir-rouler-velo":[{"date":"2017-12-31","value":0},{"date":"2018-12-31","value":0},{"date":"2019-03-31","value":0},{"date":"2019-04-30","value":10},{"date":"2020-11-30","value":303},{"date":"2020-12-31","value":303},{"date":"2021-01-31","value":303},{"date":"2021-02-28","value":303},{"date":"2021-03-31","value":323},{"date":"2021-06-30","value":241},{"date":"2021-09-30","value":241}],"nb-cycle-aisance-aquatique":[{"date":"2020-12-31","value":0}],"targets":{"nb-cycle-aisance-aquatique":{"target":1671,"target_date":"2022-12-31"},"nb-attestations-savoir-rouler-velo":{"target":3685,"target_date":"2022-12-31"}}},{"dep":"77","libelle":"Seine-et-Marne","values":{"nb-attestations-savoir-rouler-velo":{"value":630,"value_date":"2021-09-30"},"nb-cycle-aisance-aquatique":{"value":313,"value_date":"2020-12-31"}},"nb-attestations-savoir-rouler-velo":[{"date":"2017-12-31","value":0},{"date":"2018-12-31","value":0},{"date":"2019-03-31","value":0},{"date":"2019-04-30","value":0},{"date":"2020-11-30","value":0},{"date":"2020-12-31","value":0},{"date":"2021-01-31","value":0},{"date":"2021-02-28","value":0},{"date":"2021-03-31","value":18},{"date":"2021-06-30","value":285},{"date":"2021-09-30","value":630}],"nb-cycle-aisance-aquatique":[{"date":"2020-12-31","value":313}],"targets":{"nb-cycle-aisance-aquatique":{"target":2215,"target_date":"2022-12-31"},"nb-attestations-savoir-rouler-velo":{"target":4851,"target_date":"2022-12-31"}}},{"dep":"78","libelle":"Yvelines","values":{"nb-attestations-savoir-rouler-velo":{"value":2030,"value_date":"2021-09-30"},"nb-cycle-aisance-aquatique":{"value":153,"value_date":"2020-12-31"}},"nb-attestations-savoir-rouler-velo":[{"date":"2017-12-31","value":0},{"date":"2018-12-31","value":0},{"date":"2019-03-31","value":0},{"date":"2019-04-30","value":38},{"date":"2020-11-30","value":174},{"date":"2020-12-31","value":222},{"date":"2021-01-31","value":222},{"date":"2021-02-28","value":222},{"date":"2021-03-31","value":296},{"date":"2021-06-30","value":1846},{"date":"2021-09-30","value":2030}],"nb-cycle-aisance-aquatique":[{"date":"2020-12-31","value":153}],"targets":{"nb-cycle-aisance-aquatique":{"target":1644,"target_date":"2022-12-31"},"nb-attestations-savoir-rouler-velo":{"target":4861,"target_date":"2022-12-31"}}},{"dep":"79","libelle":"Deux-Sèvres","values":{"nb-attestations-savoir-rouler-velo":{"value":669,"value_date":"2021-09-30"},"nb-cycle-aisance-aquatique":{"value":0,"value_date":"2020-12-31"}},"nb-attestations-savoir-rouler-velo":[{"date":"2017-12-31","value":0},{"date":"2018-12-31","value":0},{"date":"2019-03-31","value":0},{"date":"2019-04-30","value":0},{"date":"2020-11-30","value":0},{"date":"2020-12-31","value":0},{"date":"2021-01-31","value":0},{"date":"2021-02-28","value":25},{"date":"2021-03-31","value":50},{"date":"2021-06-30","value":650},{"date":"2021-09-30","value":669}],"nb-cycle-aisance-aquatique":[{"date":"2020-12-31","value":0}],"targets":{"nb-cycle-aisance-aquatique":{"target":457,"target_date":"2022-12-31"},"nb-attestations-savoir-rouler-velo":{"target":1111,"target_date":"2022-12-31"}}},{"dep":"80","libelle":"Somme","values":{"nb-attestations-savoir-rouler-velo":{"value":46,"value_date":"2021-09-30"},"nb-cycle-aisance-aquatique":{"value":0,"value_date":"2020-12-31"}},"nb-attestations-savoir-rouler-velo":[{"date":"2017-12-31","value":0},{"date":"2018-12-31","value":0},{"date":"2019-03-31","value":0},{"date":"2019-04-30","value":8},{"date":"2020-11-30","value":26},{"date":"2020-12-31","value":35},{"date":"2021-01-31","value":35},{"date":"2021-02-28","value":35},{"date":"2021-03-31","value":41},{"date":"2021-06-30","value":41},{"date":"2021-09-30","value":46}],"nb-cycle-aisance-aquatique":[{"date":"2020-12-31","value":0}],"targets":{"nb-cycle-aisance-aquatique":{"target":725,"target_date":"2022-12-31"},"nb-attestations-savoir-rouler-velo":{"target":1635,"target_date":"2022-12-31"}}},{"dep":"81","libelle":"Tarn","values":{"nb-attestations-savoir-rouler-velo":{"value":263,"value_date":"2021-09-30"},"nb-cycle-aisance-aquatique":{"value":0,"value_date":"2020-12-31"}},"nb-attestations-savoir-rouler-velo":[{"date":"2017-12-31","value":0},{"date":"2018-12-31","value":0},{"date":"2019-03-31","value":0},{"date":"2019-04-30","value":11},{"date":"2020-11-30","value":11},{"date":"2020-12-31","value":11},{"date":"2021-01-31","value":11},{"date":"2021-02-28","value":11},{"date":"2021-03-31","value":18},{"date":"2021-06-30","value":181},{"date":"2021-09-30","value":263}],"nb-cycle-aisance-aquatique":[{"date":"2020-12-31","value":0}],"targets":{"nb-cycle-aisance-aquatique":{"target":463,"target_date":"2022-12-31"},"nb-attestations-savoir-rouler-velo":{"target":1086,"target_date":"2022-12-31"}}},{"dep":"82","libelle":"Tarn-et-Garonne","values":{"nb-attestations-savoir-rouler-velo":{"value":524,"value_date":"2021-09-30"},"nb-cycle-aisance-aquatique":{"value":0,"value_date":"2020-12-31"}},"nb-attestations-savoir-rouler-velo":[{"date":"2017-12-31","value":0},{"date":"2018-12-31","value":0},{"date":"2019-03-31","value":0},{"date":"2019-04-30","value":0},{"date":"2020-11-30","value":0},{"date":"2020-12-31","value":11},{"date":"2021-01-31","value":11},{"date":"2021-02-28","value":11},{"date":"2021-03-31","value":35},{"date":"2021-06-30","value":370},{"date":"2021-09-30","value":524}],"nb-cycle-aisance-aquatique":[{"date":"2020-12-31","value":0}],"targets":{"nb-cycle-aisance-aquatique":{"target":352,"target_date":"2022-12-31"},"nb-attestations-savoir-rouler-velo":{"target":825,"target_date":"2022-12-31"}}},{"dep":"83","libelle":"Var","values":{"nb-attestations-savoir-rouler-velo":{"value":533,"value_date":"2021-09-30"},"nb-cycle-aisance-aquatique":{"value":214,"value_date":"2020-12-31"}},"nb-attestations-savoir-rouler-velo":[{"date":"2017-12-31","value":0},{"date":"2018-12-31","value":0},{"date":"2019-03-31","value":0},{"date":"2019-04-30","value":231},{"date":"2020-11-30","value":307},{"date":"2020-12-31","value":307},{"date":"2021-01-31","value":307},{"date":"2021-02-28","value":307},{"date":"2021-03-31","value":333},{"date":"2021-06-30","value":371},{"date":"2021-09-30","value":533}],"nb-cycle-aisance-aquatique":[{"date":"2020-12-31","value":214}],"targets":{"nb-cycle-aisance-aquatique":{"target":1292,"target_date":"2022-12-31"},"nb-attestations-savoir-rouler-velo":{"target":2897,"target_date":"2022-12-31"}}},{"dep":"84","libelle":"Vaucluse","values":{"nb-attestations-savoir-rouler-velo":{"value":276,"value_date":"2021-09-30"},"nb-cycle-aisance-aquatique":{"value":0,"value_date":"2020-12-31"}},"nb-attestations-savoir-rouler-velo":[{"date":"2017-12-31","value":0},{"date":"2018-12-31","value":0},{"date":"2019-03-31","value":0},{"date":"2019-04-30","value":0},{"date":"2020-11-30","value":9},{"date":"2020-12-31","value":26},{"date":"2021-01-31","value":26},{"date":"2021-02-28","value":56},{"date":"2021-03-31","value":67},{"date":"2021-06-30","value":212},{"date":"2021-09-30","value":276}],"nb-cycle-aisance-aquatique":[{"date":"2020-12-31","value":0}],"targets":{"nb-cycle-aisance-aquatique":{"target":782,"target_date":"2022-12-31"},"nb-attestations-savoir-rouler-velo":{"target":1748,"target_date":"2022-12-31"}}},{"dep":"85","libelle":"Vendée","values":{"nb-attestations-savoir-rouler-velo":{"value":331,"value_date":"2021-09-30"},"nb-cycle-aisance-aquatique":{"value":0,"value_date":"2020-12-31"}},"nb-attestations-savoir-rouler-velo":[{"date":"2017-12-31","value":0},{"date":"2018-12-31","value":0},{"date":"2019-03-31","value":0},{"date":"2019-04-30","value":0},{"date":"2020-11-30","value":15},{"date":"2020-12-31","value":15},{"date":"2021-01-31","value":15},{"date":"2021-02-28","value":15},{"date":"2021-03-31","value":39},{"date":"2021-06-30","value":39},{"date":"2021-09-30","value":331}],"nb-cycle-aisance-aquatique":[{"date":"2020-12-31","value":0}],"targets":{"nb-cycle-aisance-aquatique":{"target":880,"target_date":"2022-12-31"},"nb-attestations-savoir-rouler-velo":{"target":2069,"target_date":"2022-12-31"}}},{"dep":"86","libelle":"Vienne","values":{"nb-attestations-savoir-rouler-velo":{"value":1433,"value_date":"2021-09-30"},"nb-cycle-aisance-aquatique":{"value":41,"value_date":"2020-12-31"}},"nb-attestations-savoir-rouler-velo":[{"date":"2017-12-31","value":0},{"date":"2018-12-31","value":0},{"date":"2019-03-31","value":0},{"date":"2019-04-30","value":26},{"date":"2020-11-30","value":51},{"date":"2020-12-31","value":51},{"date":"2021-01-31","value":51},{"date":"2021-02-28","value":51},{"date":"2021-03-31","value":55},{"date":"2021-06-30","value":1407},{"date":"2021-09-30","value":1433}],"nb-cycle-aisance-aquatique":[{"date":"2020-12-31","value":41}],"targets":{"nb-cycle-aisance-aquatique":{"target":523,"target_date":"2022-12-31"},"nb-attestations-savoir-rouler-velo":{"target":1196,"target_date":"2022-12-31"}}},{"dep":"87","libelle":"Haute-Vienne","values":{"nb-attestations-savoir-rouler-velo":{"value":1024,"value_date":"2021-09-30"},"nb-cycle-aisance-aquatique":{"value":0,"value_date":"2020-12-31"}},"nb-attestations-savoir-rouler-velo":[{"date":"2017-12-31","value":0},{"date":"2018-12-31","value":0},{"date":"2019-03-31","value":0},{"date":"2019-04-30","value":104},{"date":"2020-11-30","value":164},{"date":"2020-12-31","value":204},{"date":"2021-01-31","value":204},{"date":"2021-02-28","value":204},{"date":"2021-03-31","value":208},{"date":"2021-06-30","value":996},{"date":"2021-09-30","value":1024}],"nb-cycle-aisance-aquatique":[{"date":"2020-12-31","value":0}],"targets":{"nb-cycle-aisance-aquatique":{"target":414,"target_date":"2022-12-31"},"nb-attestations-savoir-rouler-velo":{"target":940,"target_date":"2022-12-31"}}},{"dep":"88","libelle":"Vosges","values":{"nb-attestations-savoir-rouler-velo":{"value":341,"value_date":"2021-09-30"},"nb-cycle-aisance-aquatique":{"value":52,"value_date":"2020-12-31"}},"nb-attestations-savoir-rouler-velo":[{"date":"2017-12-31","value":0},{"date":"2018-12-31","value":0},{"date":"2019-03-31","value":0},{"date":"2019-04-30","value":44},{"date":"2020-11-30","value":200},{"date":"2020-12-31","value":200},{"date":"2021-01-31","value":200},{"date":"2021-02-28","value":200},{"date":"2021-03-31","value":211},{"date":"2021-06-30","value":275},{"date":"2021-09-30","value":341}],"nb-cycle-aisance-aquatique":[{"date":"2020-12-31","value":52}],"targets":{"nb-cycle-aisance-aquatique":{"target":422,"target_date":"2022-12-31"},"nb-attestations-savoir-rouler-velo":{"target":984,"target_date":"2022-12-31"}}},{"dep":"89","libelle":"Yonne","values":{"nb-attestations-savoir-rouler-velo":{"value":388,"value_date":"2021-09-30"},"nb-cycle-aisance-aquatique":{"value":0,"value_date":"2020-12-31"}},"nb-attestations-savoir-rouler-velo":[{"date":"2017-12-31","value":0},{"date":"2018-12-31","value":0},{"date":"2019-03-31","value":0},{"date":"2019-04-30","value":201},{"date":"2020-11-30","value":201},{"date":"2020-12-31","value":201},{"date":"2021-01-31","value":201},{"date":"2021-02-28","value":201},{"date":"2021-03-31","value":237},{"date":"2021-06-30","value":250},{"date":"2021-09-30","value":388}],"nb-cycle-aisance-aquatique":[{"date":"2020-12-31","value":0}],"targets":{"nb-cycle-aisance-aquatique":{"target":411,"target_date":"2022-12-31"},"nb-attestations-savoir-rouler-velo":{"target":964,"target_date":"2022-12-31"}}},{"dep":"90","libelle":"Territoire de Belfort","values":{"nb-attestations-savoir-rouler-velo":{"value":210,"value_date":"2021-09-30"},"nb-cycle-aisance-aquatique":{"value":0,"value_date":"2020-12-31"}},"nb-attestations-savoir-rouler-velo":[{"date":"2017-12-31","value":0},{"date":"2018-12-31","value":0},{"date":"2019-03-31","value":0},{"date":"2019-04-30","value":0},{"date":"2020-11-30","value":0},{"date":"2020-12-31","value":0},{"date":"2021-01-31","value":0},{"date":"2021-02-28","value":0},{"date":"2021-03-31","value":3},{"date":"2021-06-30","value":185},{"date":"2021-09-30","value":210}],"nb-cycle-aisance-aquatique":[{"date":"2020-12-31","value":0}],"targets":{"nb-cycle-aisance-aquatique":{"target":182,"target_date":"2022-12-31"},"nb-attestations-savoir-rouler-velo":{"target":402,"target_date":"2022-12-31"}}},{"dep":"91","libelle":"Essonne","values":{"nb-attestations-savoir-rouler-velo":{"value":854,"value_date":"2021-09-30"},"nb-cycle-aisance-aquatique":{"value":375,"value_date":"2020-12-31"}},"nb-attestations-savoir-rouler-velo":[{"date":"2017-12-31","value":0},{"date":"2018-12-31","value":0},{"date":"2019-03-31","value":0},{"date":"2019-04-30","value":15},{"date":"2020-11-30","value":49},{"date":"2020-12-31","value":49},{"date":"2021-01-31","value":49},{"date":"2021-02-28","value":60},{"date":"2021-03-31","value":82},{"date":"2021-06-30","value":843},{"date":"2021-09-30","value":854}],"nb-cycle-aisance-aquatique":[{"date":"2020-12-31","value":375}],"targets":{"nb-cycle-aisance-aquatique":{"target":2083,"target_date":"2022-12-31"},"nb-attestations-savoir-rouler-velo":{"target":4470,"target_date":"2022-12-31"}}},{"dep":"92","libelle":"Hauts-de-Seine","values":{"nb-attestations-savoir-rouler-velo":{"value":75,"value_date":"2021-09-30"},"nb-cycle-aisance-aquatique":{"value":0,"value_date":"2020-12-31"}},"nb-attestations-savoir-rouler-velo":[{"date":"2017-12-31","value":0},{"date":"2018-12-31","value":0},{"date":"2019-03-31","value":0},{"date":"2019-04-30","value":25},{"date":"2020-11-30","value":25},{"date":"2020-12-31","value":25},{"date":"2021-01-31","value":25},{"date":"2021-02-28","value":25},{"date":"2021-03-31","value":51},{"date":"2021-06-30","value":75},{"date":"2021-09-30","value":75}],"nb-cycle-aisance-aquatique":[{"date":"2020-12-31","value":0}],"targets":{"nb-cycle-aisance-aquatique":{"target":2238,"target_date":"2022-12-31"},"nb-attestations-savoir-rouler-velo":{"target":4672,"target_date":"2022-12-31"}}},{"dep":"93","libelle":"Seine-Saint-Denis","values":{"nb-attestations-savoir-rouler-velo":{"value":655,"value_date":"2021-09-30"},"nb-cycle-aisance-aquatique":{"value":669,"value_date":"2020-12-31"}},"nb-attestations-savoir-rouler-velo":[{"date":"2017-12-31","value":0},{"date":"2018-12-31","value":0},{"date":"2019-03-31","value":0},{"date":"2019-04-30","value":144},{"date":"2020-11-30","value":144},{"date":"2020-12-31","value":255},{"date":"2021-01-31","value":255},{"date":"2021-02-28","value":255},{"date":"2021-03-31","value":336},{"date":"2021-06-30","value":613},{"date":"2021-09-30","value":655}],"nb-cycle-aisance-aquatique":[{"date":"2020-12-31","value":669}],"targets":{"nb-cycle-aisance-aquatique":{"target":2748,"target_date":"2022-12-31"},"nb-attestations-savoir-rouler-velo":{"target":5587,"target_date":"2022-12-31"}}},{"dep":"94","libelle":"Val-de-Marne","values":{"nb-attestations-savoir-rouler-velo":{"value":1497,"value_date":"2021-09-30"},"nb-cycle-aisance-aquatique":{"value":27,"value_date":"2020-12-31"}},"nb-attestations-savoir-rouler-velo":[{"date":"2017-12-31","value":0},{"date":"2018-12-31","value":0},{"date":"2019-03-31","value":0},{"date":"2019-04-30","value":1005},{"date":"2020-11-30","value":1005},{"date":"2020-12-31","value":1005},{"date":"2021-01-31","value":1018},{"date":"2021-02-28","value":1018},{"date":"2021-03-31","value":1036},{"date":"2021-06-30","value":1189},{"date":"2021-09-30","value":1497}],"nb-cycle-aisance-aquatique":[{"date":"2020-12-31","value":27}],"targets":{"nb-cycle-aisance-aquatique":{"target":2023,"target_date":"2022-12-31"},"nb-attestations-savoir-rouler-velo":{"target":4203,"target_date":"2022-12-31"}}},{"dep":"95","libelle":"Val-d'Oise","values":{"nb-attestations-savoir-rouler-velo":{"value":584,"value_date":"2021-09-30"},"nb-cycle-aisance-aquatique":{"value":265,"value_date":"2020-12-31"}},"nb-attestations-savoir-rouler-velo":[{"date":"2017-12-31","value":0},{"date":"2018-12-31","value":0},{"date":"2019-03-31","value":0},{"date":"2019-04-30","value":98},{"date":"2020-11-30","value":248},{"date":"2020-12-31","value":248},{"date":"2021-01-31","value":248},{"date":"2021-02-28","value":255},{"date":"2021-03-31","value":278},{"date":"2021-06-30","value":395},{"date":"2021-09-30","value":584}],"nb-cycle-aisance-aquatique":[{"date":"2020-12-31","value":265}],"targets":{"nb-cycle-aisance-aquatique":{"target":2117,"target_date":"2022-12-31"},"nb-attestations-savoir-rouler-velo":{"target":4442,"target_date":"2022-12-31"}}},{"dep":"971","libelle":"Guadeloupe","values":{"nb-attestations-savoir-rouler-velo":{"value":548,"value_date":"2021-09-30"},"nb-cycle-aisance-aquatique":{"value":165,"value_date":"2020-12-31"}},"nb-attestations-savoir-rouler-velo":[{"date":"2017-12-31","value":0},{"date":"2018-12-31","value":0},{"date":"2019-03-31","value":0},{"date":"2019-04-30","value":20},{"date":"2020-11-30","value":278},{"date":"2020-12-31","value":304},{"date":"2021-01-31","value":304},{"date":"2021-02-28","value":304},{"date":"2021-03-31","value":304},{"date":"2021-06-30","value":466},{"date":"2021-09-30","value":548}],"nb-cycle-aisance-aquatique":[{"date":"2020-12-31","value":165}],"targets":{"nb-cycle-aisance-aquatique":{"target":622,"target_date":"2022-12-31"},"nb-attestations-savoir-rouler-velo":{"target":1437,"target_date":"2022-12-31"}}},{"dep":"972","libelle":"Martinique","values":{"nb-attestations-savoir-rouler-velo":{"value":90,"value_date":"2021-09-30"},"nb-cycle-aisance-aquatique":{"value":0,"value_date":"2020-12-31"}},"nb-attestations-savoir-rouler-velo":[{"date":"2017-12-31","value":0},{"date":"2018-12-31","value":0},{"date":"2019-03-31","value":0},{"date":"2019-04-30","value":0},{"date":"2020-11-30","value":112},{"date":"2020-12-31","value":112},{"date":"2021-01-31","value":112},{"date":"2021-02-28","value":112},{"date":"2021-03-31","value":158},{"date":"2021-06-30","value":90},{"date":"2021-09-30","value":90}],"nb-cycle-aisance-aquatique":[{"date":"2020-12-31","value":0}],"targets":{"nb-cycle-aisance-aquatique":{"target":464,"target_date":"2022-12-31"},"nb-attestations-savoir-rouler-velo":{"target":1130,"target_date":"2022-12-31"}}},{"dep":"973","libelle":"Guyane","values":{"nb-attestations-savoir-rouler-velo":{"value":0,"value_date":"2021-09-30"},"nb-cycle-aisance-aquatique":{"value":0,"value_date":"2020-12-31"}},"nb-attestations-savoir-rouler-velo":[{"date":"2017-12-31","value":0},{"date":"2018-12-31","value":0},{"date":"2019-03-31","value":0},{"date":"2019-04-30","value":0},{"date":"2020-11-30","value":0},{"date":"2020-12-31","value":0},{"date":"2021-01-31","value":0},{"date":"2021-02-28","value":0},{"date":"2021-03-31","value":0},{"date":"2021-06-30","value":0},{"date":"2021-09-30","value":0}],"nb-cycle-aisance-aquatique":[{"date":"2020-12-31","value":0}],"targets":{"nb-cycle-aisance-aquatique":{"target":612,"target_date":"2022-12-31"},"nb-attestations-savoir-rouler-velo":{"target":1333,"target_date":"2022-12-31"}}},{"dep":"974","libelle":"La Réunion","values":{"nb-attestations-savoir-rouler-velo":{"value":3108,"value_date":"2021-09-30"},"nb-cycle-aisance-aquatique":{"value":38,"value_date":"2020-12-31"}},"nb-attestations-savoir-rouler-velo":[{"date":"2017-12-31","value":0},{"date":"2018-12-31","value":0},{"date":"2019-03-31","value":0},{"date":"2019-04-30","value":2794},{"date":"2020-11-30","value":2800},{"date":"2020-12-31","value":2800},{"date":"2021-01-31","value":2800},{"date":"2021-02-28","value":2800},{"date":"2021-03-31","value":2840},{"date":"2021-06-30","value":3108},{"date":"2021-09-30","value":3108}],"nb-cycle-aisance-aquatique":[{"date":"2020-12-31","value":38}],"targets":{"nb-cycle-aisance-aquatique":{"target":1558,"target_date":"2022-12-31"},"nb-attestations-savoir-rouler-velo":{"target":3579,"target_date":"2022-12-31"}}},{"dep":"976","libelle":"Mayotte","values":{"nb-attestations-savoir-rouler-velo":{"value":0,"value_date":"2021-09-30"},"nb-cycle-aisance-aquatique":{"value":0,"value_date":"2020-12-31"}},"nb-attestations-savoir-rouler-velo":[{"date":"2017-12-31","value":0},{"date":"2018-12-31","value":0},{"date":"2019-03-31","value":0},{"date":"2019-04-30","value":0},{"date":"2020-11-30","value":0},{"date":"2020-12-31","value":0},{"date":"2021-01-31","value":0},{"date":"2021-02-28","value":0},{"date":"2021-03-31","value":0},{"date":"2021-06-30","value":0},{"date":"2021-09-30","value":0}],"nb-cycle-aisance-aquatique":[{"date":"2020-12-31","value":0}],"targets":{"nb-cycle-aisance-aquatique":{"target":740,"target_date":"2022-12-31"},"nb-attestations-savoir-rouler-velo":{"target":1771,"target_date":"2022-12-31"}}}]
