[{"ovq":[{"id_ovq":"OVQ-PVL","indicateurs":[{"km-amenagement-cyclables-securises":[{"latest_value":57014,"latest_value_date":"2022-12-31","initial_value":40201,"initial_value_date":"2017-12-31","progression_last_update_percentage":14,"progression_last_update_date":"2020-09-30","progression_last_update":49922,"progression_percentage":42,"progression":16813,"target":55477,"target_percentage":100,"target_date":"2022-03-31"}]}]},{"id_ovq":"OVQ-ZFE","indicateurs":[{"nb-habitants-zfe":[{"latest_value":7984997,"latest_value_date":"2022-12-31","initial_value":2187526,"initial_value_date":"2017-12-31","progression_last_update_percentage":null,"progression_last_update_date":null,"progression_last_update":null,"progression_percentage":265,"progression":5797471,"target":9000000,"target_percentage":85,"target_date":"2022-12-31"}]}]},{"id_ovq":"OVQ-VPA","indicateurs":[{"nb-primes-conversion":[{"latest_value":1781317,"latest_value_date":"2022-12-31","initial_value":0,"initial_value_date":"2018-01-31","progression_last_update_percentage":102,"progression_last_update_date":"2020-09-30","progression_last_update":880459,"progression_percentage":null,"progression":1781317,"target":1500000,"target_percentage":100,"target_date":"2022-06-30"}]},{"nb-points-recharge":[{"latest_value":77325,"latest_value_date":"2022-12-31","initial_value":27745,"initial_value_date":"2019-09-30","progression_last_update_percentage":null,"progression_last_update_date":null,"progression_last_update":null,"progression_percentage":179,"progression":49580,"target":100000,"target_percentage":69,"target_date":"2022-03-31"}]}]},{"id_ovq":"OVQ-PUU","indicateurs":[{"nb-francais-emballages-bac-jaune":[{"latest_value":63200000,"latest_value_date":"2022-12-31","initial_value":15590000,"initial_value_date":"2017-06-30","progression_last_update_percentage":100,"progression_last_update_date":"2020-06-30","progression_last_update":31650000,"progression_percentage":305,"progression":47610000,"target":66460000,"target_percentage":94,"target_date":"2022-12-31"}]}]},{"id_ovq":"OVQ-PLF","indicateurs":[{"nb-km-lignes-regenerees":[{"latest_value":1281,"latest_value_date":"2022-12-31","initial_value":0,"initial_value_date":"2017-01-31","progression_last_update_percentage":null,"progression_last_update_date":null,"progression_last_update":null,"progression_percentage":null,"progression":1281,"target":1499,"target_percentage":85,"target_date":"2022-12-31"}]}]}]}]
