[{"values":{"nb-entreprises-industrielles-agricoles":{"value":8972,"value_date":"2023-01-31"}},"nb-entreprises-industrielles-agricoles":[{"date":"2020-01-31","value":0},{"date":"2020-02-29","value":0},{"date":"2020-03-31","value":0},{"date":"2020-04-30","value":0},{"date":"2020-05-31","value":0},{"date":"2020-06-30","value":0},{"date":"2020-07-31","value":0},{"date":"2020-08-31","value":0},{"date":"2020-09-30","value":0},{"date":"2020-10-31","value":0},{"date":"2020-11-30","value":253},{"date":"2020-12-31","value":438},{"date":"2021-01-31","value":562},{"date":"2021-02-28","value":742},{"date":"2021-03-31","value":1680},{"date":"2021-04-30","value":2113},{"date":"2021-05-31","value":3658},{"date":"2021-06-30","value":3807},{"date":"2021-07-31","value":7867},{"date":"2021-08-31","value":8235},{"date":"2021-09-30","value":8890},{"date":"2021-10-31","value":9617},{"date":"2021-11-30","value":9725},{"date":"2021-12-31","value":9770},{"date":"2022-01-31","value":9762},{"date":"2022-02-28","value":8555},{"date":"2022-03-31","value":8689},{"date":"2022-04-30","value":8831},{"date":"2022-05-31","value":8882},{"date":"2022-06-30","value":8954},{"date":"2022-07-31","value":8962},{"date":"2022-08-31","value":8961},{"date":"2022-09-30","value":8958},{"date":"2022-10-31","value":8958},{"date":"2022-11-30","value":8973},{"date":"2022-12-31","value":8972},{"date":"2023-01-31","value":8972}],"targets":{"nb-entreprises-industrielles-agricoles":{"target":null,"target_date":null}}}]
