[{"reg":"84","libelle":"Auvergne-Rhône-Alpes","values":{"nb-francais-emballages-bac-jaune":{"value":5270000,"value_date":"2022-06-30"}},"nb-francais-emballages-bac-jaune":[{"date":"2017-06-30","value":800000},{"date":"2017-12-31","value":800000},{"date":"2018-06-30","value":800000},{"date":"2018-12-31","value":800000},{"date":"2019-06-30","value":1290000},{"date":"2019-12-31","value":1370000},{"date":"2020-06-30","value":2930000},{"date":"2020-12-31","value":3040000},{"date":"2021-06-30","value":3830000},{"date":"2021-12-31","value":4570000},{"date":"2022-06-30","value":5270000}],"targets":{"nb-francais-emballages-bac-jaune":{"target":7950000,"target_date":"2022-12-31"}}},{"reg":"32","libelle":"Hauts-de-France","values":{"nb-francais-emballages-bac-jaune":{"value":2390000,"value_date":"2022-06-30"}},"nb-francais-emballages-bac-jaune":[{"date":"2017-06-30","value":950000},{"date":"2017-12-31","value":950000},{"date":"2018-06-30","value":950000},{"date":"2018-12-31","value":950000},{"date":"2019-06-30","value":1150000},{"date":"2019-12-31","value":1340000},{"date":"2020-06-30","value":1810000},{"date":"2020-12-31","value":1810000},{"date":"2021-06-30","value":1900000},{"date":"2021-12-31","value":2390000},{"date":"2022-06-30","value":2390000}],"targets":{"nb-francais-emballages-bac-jaune":{"target":5990000,"target_date":"2022-12-31"}}},{"reg":"93","libelle":"Provence-Alpes-Côte d'Azur","values":{"nb-francais-emballages-bac-jaune":{"value":3670000,"value_date":"2022-06-30"}},"nb-francais-emballages-bac-jaune":[{"date":"2017-06-30","value":1140000},{"date":"2017-12-31","value":1140000},{"date":"2018-06-30","value":1140000},{"date":"2018-12-31","value":1310000},{"date":"2019-06-30","value":2220000},{"date":"2019-12-31","value":2250000},{"date":"2020-06-30","value":2390000},{"date":"2020-12-31","value":2490000},{"date":"2021-06-30","value":2660000},{"date":"2021-12-31","value":3140000},{"date":"2022-06-30","value":3670000}],"targets":{"nb-francais-emballages-bac-jaune":{"target":5020000,"target_date":"2022-12-31"}}},{"reg":"44","libelle":"Grand Est","values":{"nb-francais-emballages-bac-jaune":{"value":3100000,"value_date":"2022-06-30"}},"nb-francais-emballages-bac-jaune":[{"date":"2017-06-30","value":820000},{"date":"2017-12-31","value":820000},{"date":"2018-06-30","value":820000},{"date":"2018-12-31","value":830000},{"date":"2019-06-30","value":850000},{"date":"2019-12-31","value":850000},{"date":"2020-06-30","value":1390000},{"date":"2020-12-31","value":1760000},{"date":"2021-06-30","value":2280000},{"date":"2021-12-31","value":2300000},{"date":"2022-06-30","value":3100000}],"targets":{"nb-francais-emballages-bac-jaune":{"target":5550000,"target_date":"2022-12-31"}}},{"reg":"76","libelle":"Occitanie","values":{"nb-francais-emballages-bac-jaune":{"value":3670000,"value_date":"2022-06-30"}},"nb-francais-emballages-bac-jaune":[{"date":"2017-06-30","value":1560000},{"date":"2017-12-31","value":1560000},{"date":"2018-06-30","value":1560000},{"date":"2018-12-31","value":1570000},{"date":"2019-06-30","value":2000000},{"date":"2019-12-31","value":2440000},{"date":"2020-06-30","value":2830000},{"date":"2020-12-31","value":2990000},{"date":"2021-06-30","value":3130000},{"date":"2021-12-31","value":3450000},{"date":"2022-06-30","value":3670000}],"targets":{"nb-francais-emballages-bac-jaune":{"target":5830000,"target_date":"2022-12-31"}}},{"reg":"28","libelle":"Normandie","values":{"nb-francais-emballages-bac-jaune":{"value":2800000,"value_date":"2022-06-30"}},"nb-francais-emballages-bac-jaune":[{"date":"2017-06-30","value":1310000},{"date":"2017-12-31","value":1310000},{"date":"2018-06-30","value":1310000},{"date":"2018-12-31","value":1370000},{"date":"2019-06-30","value":1480000},{"date":"2019-12-31","value":1590000},{"date":"2020-06-30","value":1790000},{"date":"2020-12-31","value":2000000},{"date":"2021-06-30","value":2300000},{"date":"2021-12-31","value":2710000},{"date":"2022-06-30","value":2800000}],"targets":{"nb-francais-emballages-bac-jaune":{"target":3320000,"target_date":"2022-12-31"}}},{"reg":"75","libelle":"Nouvelle-Aquitaine","values":{"nb-francais-emballages-bac-jaune":{"value":3940000,"value_date":"2022-06-30"}},"nb-francais-emballages-bac-jaune":[{"date":"2017-06-30","value":2050000},{"date":"2017-12-31","value":2050000},{"date":"2018-06-30","value":2050000},{"date":"2018-12-31","value":2210000},{"date":"2019-06-30","value":2430000},{"date":"2019-12-31","value":2660000},{"date":"2020-06-30","value":2920000},{"date":"2020-12-31","value":3370000},{"date":"2021-06-30","value":3650000},{"date":"2021-12-31","value":3690000},{"date":"2022-06-30","value":3940000}],"targets":{"nb-francais-emballages-bac-jaune":{"target":5940000,"target_date":"2022-12-31"}}},{"reg":"24","libelle":"Centre-Val de Loire","values":{"nb-francais-emballages-bac-jaune":{"value":1520000,"value_date":"2022-06-30"}},"nb-francais-emballages-bac-jaune":[{"date":"2017-06-30","value":120000},{"date":"2017-12-31","value":120000},{"date":"2018-06-30","value":120000},{"date":"2018-12-31","value":120000},{"date":"2019-06-30","value":190000},{"date":"2019-12-31","value":190000},{"date":"2020-06-30","value":190000},{"date":"2020-12-31","value":190000},{"date":"2021-06-30","value":740000},{"date":"2021-12-31","value":1000000},{"date":"2022-06-30","value":1520000}],"targets":{"nb-francais-emballages-bac-jaune":{"target":2570000,"target_date":"2022-12-31"}}},{"reg":"27","libelle":"Bourgogne-Franche-Comté","values":{"nb-francais-emballages-bac-jaune":{"value":1690000,"value_date":"2022-06-30"}},"nb-francais-emballages-bac-jaune":[{"date":"2017-06-30","value":1010000},{"date":"2017-12-31","value":1010000},{"date":"2018-06-30","value":1010000},{"date":"2018-12-31","value":1010000},{"date":"2019-06-30","value":1220000},{"date":"2019-12-31","value":1230000},{"date":"2020-06-30","value":1410000},{"date":"2020-12-31","value":1410000},{"date":"2021-06-30","value":1410000},{"date":"2021-12-31","value":1550000},{"date":"2022-06-30","value":1690000}],"targets":{"nb-francais-emballages-bac-jaune":{"target":2810000,"target_date":"2022-12-31"}}},{"reg":"53","libelle":"Bretagne","values":{"nb-francais-emballages-bac-jaune":{"value":2710000,"value_date":"2022-06-30"}},"nb-francais-emballages-bac-jaune":[{"date":"2017-06-30","value":1240000},{"date":"2017-12-31","value":1240000},{"date":"2018-06-30","value":1240000},{"date":"2018-12-31","value":1770000},{"date":"2019-06-30","value":1940000},{"date":"2019-12-31","value":1940000},{"date":"2020-06-30","value":1940000},{"date":"2020-12-31","value":2460000},{"date":"2021-06-30","value":2460000},{"date":"2021-12-31","value":2570000},{"date":"2022-06-30","value":2710000}],"targets":{"nb-francais-emballages-bac-jaune":{"target":3320000,"target_date":"2022-12-31"}}},{"reg":"94","libelle":"Corse","values":{"nb-francais-emballages-bac-jaune":{"value":340000,"value_date":"2022-06-30"}},"nb-francais-emballages-bac-jaune":[{"date":"2017-06-30","value":0},{"date":"2017-12-31","value":0},{"date":"2018-06-30","value":0},{"date":"2018-12-31","value":140000},{"date":"2019-06-30","value":150000},{"date":"2019-12-31","value":340000},{"date":"2020-06-30","value":340000},{"date":"2020-12-31","value":340000},{"date":"2021-06-30","value":340000},{"date":"2021-12-31","value":340000},{"date":"2022-06-30","value":340000}],"targets":{"nb-francais-emballages-bac-jaune":{"target":340000,"target_date":"2022-12-31"}}},{"reg":"52","libelle":"Pays de la Loire","values":{"nb-francais-emballages-bac-jaune":{"value":3750000,"value_date":"2022-06-30"}},"nb-francais-emballages-bac-jaune":[{"date":"2017-06-30","value":1270000},{"date":"2017-12-31","value":1270000},{"date":"2018-06-30","value":1270000},{"date":"2018-12-31","value":1910000},{"date":"2019-06-30","value":2050000},{"date":"2019-12-31","value":2600000},{"date":"2020-06-30","value":2980000},{"date":"2020-12-31","value":3060000},{"date":"2021-06-30","value":3480000},{"date":"2021-12-31","value":3740000},{"date":"2022-06-30","value":3750000}],"targets":{"nb-francais-emballages-bac-jaune":{"target":3760000,"target_date":"2022-12-31"}}},{"reg":"11","libelle":"Île-de-France","values":{"nb-francais-emballages-bac-jaune":{"value":10570000,"value_date":"2022-06-30"}},"nb-francais-emballages-bac-jaune":[{"date":"2017-06-30","value":3320000},{"date":"2017-12-31","value":3320000},{"date":"2018-06-30","value":3320000},{"date":"2018-12-31","value":3480000},{"date":"2019-06-30","value":6680000},{"date":"2019-12-31","value":8130000},{"date":"2020-06-30","value":8730000},{"date":"2020-12-31","value":8730000},{"date":"2021-06-30","value":9120000},{"date":"2021-12-31","value":9940000},{"date":"2022-06-30","value":10570000}],"targets":{"nb-francais-emballages-bac-jaune":{"target":12180000,"target_date":"2022-12-31"}}},{"reg":"01","libelle":"Guadeloupe","values":{"nb-francais-emballages-bac-jaune":{"value":0,"value_date":"2022-06-30"}},"nb-francais-emballages-bac-jaune":[{"date":"2017-06-30","value":0},{"date":"2017-12-31","value":0},{"date":"2018-06-30","value":0},{"date":"2018-12-31","value":0},{"date":"2019-06-30","value":0},{"date":"2019-12-31","value":0},{"date":"2020-06-30","value":0},{"date":"2020-12-31","value":0},{"date":"2021-06-30","value":0},{"date":"2021-12-31","value":0},{"date":"2022-06-30","value":0}],"targets":{"nb-francais-emballages-bac-jaune":{"target":390000,"target_date":"2022-12-31"}}},{"reg":"02","libelle":"Martinique","values":{"nb-francais-emballages-bac-jaune":{"value":0,"value_date":"2022-06-30"}},"nb-francais-emballages-bac-jaune":[{"date":"2017-06-30","value":0},{"date":"2017-12-31","value":0},{"date":"2018-06-30","value":0},{"date":"2018-12-31","value":0},{"date":"2019-06-30","value":0},{"date":"2019-12-31","value":0},{"date":"2020-06-30","value":0},{"date":"2020-12-31","value":0},{"date":"2021-06-30","value":0},{"date":"2021-12-31","value":0},{"date":"2022-06-30","value":0}],"targets":{"nb-francais-emballages-bac-jaune":{"target":370000,"target_date":"2022-12-31"}}},{"reg":"03","libelle":"Guyane","values":{"nb-francais-emballages-bac-jaune":{"value":0,"value_date":"2022-06-30"}},"nb-francais-emballages-bac-jaune":[{"date":"2017-06-30","value":0},{"date":"2017-12-31","value":0},{"date":"2018-06-30","value":0},{"date":"2018-12-31","value":0},{"date":"2019-06-30","value":0},{"date":"2019-12-31","value":0},{"date":"2020-06-30","value":0},{"date":"2020-12-31","value":0},{"date":"2021-06-30","value":0},{"date":"2021-12-31","value":0},{"date":"2022-06-30","value":0}],"targets":{"nb-francais-emballages-bac-jaune":{"target":270000,"target_date":"2022-12-31"}}},{"reg":"04","libelle":"La Réunion","values":{"nb-francais-emballages-bac-jaune":{"value":0,"value_date":"2022-06-30"}},"nb-francais-emballages-bac-jaune":[{"date":"2017-06-30","value":0},{"date":"2017-12-31","value":0},{"date":"2018-06-30","value":0},{"date":"2018-12-31","value":0},{"date":"2019-06-30","value":0},{"date":"2019-12-31","value":0},{"date":"2020-06-30","value":0},{"date":"2020-12-31","value":0},{"date":"2021-06-30","value":0},{"date":"2021-12-31","value":0},{"date":"2022-06-30","value":0}],"targets":{"nb-francais-emballages-bac-jaune":{"target":850000,"target_date":"2022-12-31"}}},{"reg":"06","libelle":"Mayotte","values":{"nb-francais-emballages-bac-jaune":{"value":0,"value_date":"2022-06-30"}},"nb-francais-emballages-bac-jaune":[{"date":"2017-06-30","value":0},{"date":"2017-12-31","value":0},{"date":"2018-06-30","value":0},{"date":"2018-12-31","value":0},{"date":"2019-06-30","value":0},{"date":"2019-12-31","value":0},{"date":"2020-06-30","value":0},{"date":"2020-12-31","value":0},{"date":"2021-06-30","value":0},{"date":"2021-12-31","value":0},{"date":"2022-06-30","value":0}],"targets":{"nb-francais-emballages-bac-jaune":{"target":0,"target_date":"2022-12-31"}}}]
